Workbook

Sheet Resumen
A1: Banca Online Integral
A4: ALCANCE FUNCIONAL Y DE CONTROL
A5: Canales | C5: Banca online y billetera digital con acceso reforzado.
A6: Operaciones | C6: Transferencias propias y a terceros, pagos QR, recargas y retiros.
A7: Créditos | C7: Simulación, solicitud, evaluación, desembolso y cronograma de préstamos.
A8: Control | C8: Partida doble, conciliación, fraude, cumplimiento, roles y auditoría.
A11: INDICADOR | B11: RESULTADO | D11: QUÉ DEMUESTRA EL PROYECTO
A12: Historias de usuario | B12: =COUNTA('Historias de Usuario'!$C$4:$C$29) -> 26 | D12: Seguridad | E12: KYC, MFA/biometría, mínimo privilegio y sesiones seguras.
A13: Historias Must | B13: =COUNTIF('Historias de Usuario'!$H$4:$H$32,"Must") -> 17 | D13: Dinero | E13: Validación, autorización, contabilización, liquidación y conciliación.
A14: Historias en MVP | B14: =COUNTIF('Historias de Usuario'!$J$4:$J$32,"Sí") -> 24 | D14: Transferencias | E14: Cuentas propias, terceros, beneficiarios y controles de duplicidad.
A15: Story Points del MVP | B15: =SUMIF('Historias de Usuario'!J4:J29,"Sí",'Historias de Usuario'!I4:I29) -> 160 | D15: Préstamos | E15: Evaluación separada del solicitante y desembolso solo tras aprobación.
A16: Sprints estimados | B16: 4 | D16: Supervisión | E16: Roles diferenciados para operaciones, fraude, crédito y cumplimiento.
A17: Épicas | B17: 7 | D17: Evidencia | E17: Trazabilidad completa; los movimientos se revierten, no se borran.

Sheet Historias de Usuario
A1: Historias de usuario — MVP Bancario (Sistema de Cuentas y Transacciones)
A3: ID | B3: Épica | C3: Sprint | D3: Módulo | E3: Rol | F3: Historia de Usuario | G3: Criterios de Aceptación | H3: Prioridad (MoSCoW) | I3: Story Points | J3: En MVP
A4: HU01 | B4: Épica 1 – Identidad, Biometría y KYC | C4: Sprint 1 | D4: Registro y KYC Biométrico | E4: Cliente | F4: Como cliente nuevo, quiero registrarme escaneando mi documento de identidad y validando mi rostro con Liveness Detection para aperturar mi cuenta digital de forma segura sin ir a una agencia. | G4: CA1: El sistema debe permitir capturar y leer los datos del documento de identidad mediante OCR con precisión mínima del 95%. CA2: El sistema debe ejecutar una prueba de vida (liveness detection) para descartar fotos, videos o máscaras antes de continuar el registro. CA3: El sistema debe comparar el rostro capturado contra la foto del documento y contra la base oficial (RENIEC), continuando solo si el match supera el umbral configurado. CA4: Si la validación falla, el sistema debe informar el motivo al cliente, permitir reintentos limitados y derivar el caso a revisión manual si persiste. | H4: Must | I4: 8 | J4: Sí
A5: HU02 | C5: Sprint 1 | D5: Verificación y Activación de Cuenta | E5: Cliente | F5: Como cliente nuevo, quiero confirmar mi registro mediante un código de verificación enviado a mi correo o celular para activar mi cuenta digital antes de iniciar sesión por primera vez. | G5: CA1: El sistema debe enviar un código de verificación de un solo uso (OTP) al correo o número celular registrado inmediatamente después de completado el KYC. CA2: El sistema debe validar el código ingresado y activar la cuenta solo si coincide y no ha expirado (máximo 10 minutos). CA3: El sistema debe permitir reenviar el código hasta 3 veces respetando un tiempo de espera entre solicitudes. CA4: Una vez activada la cuenta, el sistema debe notificar al cliente y habilitarlo para iniciar sesión con sus credenciales biométricas. | H5: Must | I5: 3 | J5: Sí
A6: HU03 | C6: Sprint 1 | D6: Autenticación BioFacial y Multi-factor | E6: Cliente | F6: Como cliente, quiero ingresar a la banca móvil mediante reconocimiento facial rápido o biométricos secundarios (Huella/PIN) para acceder sin recordar contraseñas complejas. | G6: CA1: El sistema debe permitir el ingreso mediante reconocimiento facial en menos de 1.5 segundos como método principal. CA2: El sistema debe ofrecer huella digital o PIN como método alternativo ante fallas del reconocimiento facial. CA3: El sistema debe bloquear temporalmente la cuenta tras 5 intentos fallidos consecutivos y notificar al cliente. CA4: El sistema debe cerrar automáticamente la sesión tras un período de inactividad configurado y exigir una nueva autenticación. | H6: Must | I6: 5 | J6: Sí
A7: HU04 | C7: Sprint 1 | D7: Recuperación de Cuenta con Biometría | E7: Cliente | F7: Como cliente, quiero recuperar mi acceso o desbloquear mi usuario mediante re-validación de biometría facial para restablecer mis credenciales de forma autónoma. | G7: CA1: El sistema debe permitir solicitar la recuperación de acceso desde la pantalla de login sin necesidad de contraseña previa. CA2: El sistema debe re-validar el rostro del cliente contra el patrón biométrico almacenado antes de habilitar el restablecimiento. CA3: El sistema debe permitir establecer una nueva contraseña o PIN únicamente después de una validación facial exitosa. CA4: El sistema debe notificar al cliente por correo y push que sus credenciales fueron restablecidas, incluyendo fecha y dispositivo. | H7: Should | I7: 5 | J7: Sí
A8: HU05 | B8: Épica 2 – Cuentas y Transacciones | C8: Sprint 1 | D8: Consolidado de Cuentas y Saldos | E8: Cliente | F8: Como cliente, quiero consultar saldos disponibles, fondos retenidos y movimientos en tiempo real para mantener control de mi patrimonio. | G8: CA1: El sistema debe mostrar en el dashboard todas las cuentas del cliente con su tipo, número enmascarado y saldo disponible. CA2: El sistema debe diferenciar el saldo contable del saldo disponible, incluyendo fondos retenidos. CA3: El sistema debe listar los movimientos recientes de cada cuenta en tiempo real al seleccionarla. CA4: El sistema debe permitir exportar el detalle de movimientos en un formato descargable (PDF o Excel). | H8: Must | I8: 5 | J8: Sí
A9: HU06 | C9: Sprint 1 | D9: Transferencias Propias e Interbancarias | E9: Cliente | F9: Como cliente, quiero transferir dinero entre mis cuentas y a terceros (mismo banco o interbancarias inmediatas) para mover mis fondos sin comisión oculta. | G9: CA1: El sistema debe permitir transferir fondos entre cuentas propias de forma inmediata y sin costo. CA2: El sistema debe permitir transferencias interbancarias mediante CCI/CCE, validando al titular antes de confirmar la operación. CA3: El sistema debe rechazar la operación sin afectar saldos cuando los fondos sean insuficientes. CA4: El sistema debe generar un comprobante descargable con fecha, monto, cuentas involucradas y número de operación. | H9: Must | I9: 8 | J9: Sí
A10: HU08 | C10: Sprint 2 | D10: Autorización Biométrico-Facial de Pagos Altamente Sensibles | E10: Cliente | F10: Como cliente, quiero confirmar transferencias de alto monto mediante escaneo facial instantáneo para garantizar que nadie transfiera sin mi presencia física, y que el sistema restrinja transacciones según mi perfil de riesgo. | G10: CA1: El sistema debe solicitar una validación facial adicional cuando el monto de la transferencia supere el umbral de seguridad parametrizado. CA2: El sistema debe restringir el envío de la transacción hasta que la biometría sea validada exitosamente. CA3: El sistema debe aplicar límites de transacción según el perfil de riesgo del cliente. CA4: El sistema debe registrar y notificar cualquier intento fallido de autorización biométrica como evento de seguridad. | H10: Must | I10: 8 | J10: Sí
A11: HU07 | C11: Sprint 2 | D11: Gestión de Beneficiarios Frecuentes | E11: Cliente | F11: Como cliente, quiero guardar y agrupar beneficiarios frecuentes con alias y fotos para reducir errores en transferencias recurrentes. | G11: CA1: El sistema debe permitir guardar un beneficiario con alias, foto y datos de cuenta tras una transferencia exitosa. CA2: El sistema debe permitir buscar y agrupar los beneficiarios guardados por alias o nombre. CA3: El sistema debe permitir configurar un límite de monto pre-aprobado por beneficiario frecuente. CA4: El sistema debe permitir editar o eliminar un beneficiario guardado en cualquier momento. | H11: Should | I11: 3 | J11: Sí
A12: HU09 | B12: Épica 3 – Créditos Digitales | C12: Sprint 2 | D12: Simulador Inteligente de Créditos | E12: Cliente | F12: Como cliente, quiero simular monto, plazo, tasa TCEA y cuota estimada para evaluar opciones de financiamiento antes de solicitar un crédito. | G12: CA1: El sistema debe calcular la cuota estimada según el monto, plazo y tasa TCEA ingresados por el cliente. CA2: El sistema debe mostrar un cronograma de pagos provisional con el detalle de capital e intereses. CA3: El sistema debe permitir incluir opcionalmente un seguro de desgravamen en la simulación. CA4: El sistema debe permitir descargar o compartir el resultado de la simulación. | H12: Should | I12: 5 | J12: Sí
A13: HU10 | C13: Sprint 2 | D13: Solicitud y Evaluación Crediticia Automática | E13: Cliente | F13: Como cliente, quiero solicitar un préstamo digital y autorizar la consulta en centrales de riesgo para recibir una respuesta de aprobación inmediata. | G13: CA1: El sistema debe permitir enviar una solicitud de préstamo solo si el cliente autoriza la consulta en centrales de riesgo. CA2: El sistema debe validar que la solicitud tenga todos los datos obligatorios antes de iniciar la evaluación. CA3: El sistema debe consultar el motor de riesgos y el score interno para generar una pre-calificación en minutos. CA4: El sistema debe notificar al cliente el resultado de la evaluación con un estado claro (aprobado, rechazado, en revisión). | H13: Must | I13: 8 | J13: Sí
A14: HU11 | C14: Sprint 2 | D14: Firma Digital de Contrato con Biometría Facial | E14: Cliente | F14: Como cliente, quiero firmar digitalmente mi contrato de préstamo validando mi rostro como consentimiento explícito para legalizar la operación sin papeleo. | G14: CA1: El sistema debe generar el contrato de préstamo con las condiciones aprobadas antes de solicitar la firma. CA2: El sistema debe validar el rostro del cliente como mecanismo de consentimiento explícito para firmar el contrato. CA3: El sistema debe adjuntar el token facial a la firma digital certificada del documento. CA4: El sistema debe enviar el pagaré y contrato sellado al correo del cliente tras la firma. | H14: Must | I14: 8 | J14: Sí
A15: HU12 | C15: Sprint 2 | D15: Desembolso Inmediato y Programación de Cuotas | E15: Cliente | F15: Como cliente, quiero recibir el desembolso directamente en mi cuenta elegida y visualizar mi cronograma de pagos definitivo para abonar mis cuotas a tiempo. | G15: CA1: El sistema debe acreditar el monto aprobado en la cuenta elegida por el cliente de forma inmediata tras la firma. CA2: El sistema debe generar el cronograma de pagos definitivo con fechas y montos de cada cuota. CA3: El sistema debe permitir habilitar el débito automático de las cuotas desde la cuenta elegida. CA4: El sistema debe notificar al cliente la fecha y monto de cada cuota próxima a vencer. | H15: Must | I15: 5 | J15: Sí
A16: HU13 | B16: Épica 4 – Billetera y Pagos QR | C16: Sprint 3 | D16: Billetera Digital e Interoperabilidad | E16: Cliente | F16: Como cliente, quiero vincular una tarjeta/cuenta a mi billetera digital para realizar pagos rápidos sin digitar claves en comercios. | G16: CA1: El sistema debe permitir vincular una tarjeta o cuenta del cliente a la billetera digital. CA2: El sistema debe procesar pagos en comercios sin requerir el ingreso de claves adicionales. CA3: El sistema debe operar de forma interoperable con las redes de pago de la industria. CA4: El sistema debe aplicar límites diarios configurables a las operaciones express de la billetera. | H16: Must | I16: 8 | J16: Sí
A17: HU14 | C17: Sprint 3 | D17: Generación y Cobro con QR Dinámico/Estático | E17: Comercio | F17: Como comercio, quiero generar códigos QR con monto y concepto específico para cobrar a mis clientes de forma ágil sin terminal POS físico. | G17: CA1: El sistema debe permitir generar un código QR con monto y concepto específico para cada cobro. CA2: El sistema debe permitir configurar la caducidad del código QR generado. CA3: El sistema debe garantizar la interoperabilidad del QR con otras billeteras y bancos. CA4: El sistema debe notificar al comercio mediante push en el momento en que se reciba el abono. | H17: Must | I17: 5 | J17: Sí
A18: HU15 | C18: Sprint 3 | D18: Lectura y Confirmación de Pago QR | E18: Cliente | F18: Como cliente, quiero escanear un código QR para verificar la información del comercio y pagar en un solo toque. | G18: CA1: El sistema debe leer el código QR y mostrar el nombre y monto del comercio antes de confirmar el pago. CA2: El sistema debe permitir completar el pago en un solo toque cuando el monto esté dentro del límite base. CA3: El sistema debe solicitar validación biométrica adicional si el monto excede el límite base configurado. CA4: El sistema debe rechazar el pago si el código QR está vencido o ha sido alterado. | H18: Must | I18: 5 | J18: Sí
A19: HU16 | C19: Sprint 3 | D19: Pago de Servicios y Recargas Express | E19: Cliente | F19: Como cliente, quiero pagar servicios básicos (luz, agua, internet) y recargar celulares desde la app para gestionar mis pagos en un solo lugar. | G19: CA1: El sistema debe permitir buscar un servicio (luz, agua, internet) por número de suministro. CA2: El sistema debe permitir recargar celulares seleccionando operador y monto directamente desde la app. CA3: El sistema debe enviar recordatorios de vencimiento de los servicios registrados por el cliente. CA4: El sistema debe generar un comprobante estructurado por cada pago o recarga realizada. | H19: Should | I19: 5 | J19: Sí
A20: HU17 | B20: Épica 5 – Motor Transaccional | C20: Sprint 3 | D20: Motor Transaccional en Tiempo Real | E20: Sistema | F20: Como sistema core bancario, quiero procesar transacciones con control de saldos, bloqueo de fondos y prevención de doble gasto para asegurar la consistencia operativa. | G20: CA1: El sistema debe validar el saldo disponible antes de ejecutar cada transacción. CA2: El sistema debe bloquear temporalmente los fondos comprometidos hasta la confirmación final de la operación. CA3: El sistema debe garantizar que ninguna transacción se procese dos veces ante reintentos o fallas de red. CA4: El sistema debe procesar cada transacción en un tiempo menor a 200 milisegundos bajo condiciones normales de carga. | H20: Must | I20: 13 | J20: Sí
A21: HU18 | C21: Sprint 3 | D21: Contabilidad en Libro Mayor (Ledger) de Partida Doble | E21: Sistema | F21: Como sistema contable, quiero registrar débitos y créditos con partida doble e identificador único universal (UUID) para mantener la integridad financiera. | G21: CA1: El sistema debe registrar cada operación con su respectivo débito y crédito en partida doble. CA2: El sistema debe asignar un identificador único universal (UUID) a cada asiento contable generado. CA3: El sistema debe garantizar que ningún asiento quede aplicado parcialmente si falla alguno de sus movimientos. CA4: El sistema debe ejecutar un cierre contable automatizado diario verificando que el balance esté cuadrado. | H21: Must | I21: 13 | J21: Sí
A22: HU19 | C22: Sprint 3 | D22: Conciliación Bancaria y Redes de Pago | E22: Analista de operaciones | F22: Como analista de operaciones, quiero ejecutar conciliaciones automáticas entre el banco, las redes externas y la billetera para detectar inconsistencias de liquidación. | G22: CA1: El sistema debe procesar automáticamente los archivos de compensación (clearing) recibidos de las redes externas. CA2: El sistema debe comparar las operaciones del banco contra las de las redes externas y la billetera para detectar diferencias. CA3: El sistema debe generar un reporte de inconsistencias detectadas durante la conciliación. CA4: El sistema debe habilitar un flujo de reclamos para las diferencias identificadas. | H22: Must | I22: 8 | J22: Sí
A23: HU20 | B23: Épica 6 – Fraude y Cumplimiento | C23: Sprint 4 | D23: Motor Antifraude por Reglas y Anomalías Biométricas | E23: Analista de fraude | F23: Como analista de fraude, quiero recibir alertas automáticas por intentos de suplantación facial, geolocalización atípica o transacciones inusuales para mitigar pérdidas. | G23: CA1: El sistema debe detectar y alertar intentos de suplantación facial (deepfake o spoofing) durante la autenticación. CA2: El sistema debe identificar geolocalización atípica o transacciones inusuales según el patrón de comportamiento del cliente. CA3: El sistema debe bloquear preventivamente una operación cuando se detecte una alerta de alto riesgo. CA4: El sistema debe mostrar las alertas generadas en un tablero para el analista de fraude. | H23: Must | I23: 8 | J23: Sí
A24: HU21 | C24: Sprint 4 | D24: Cumplimiento PLDFT / AML y Listas Restrictivas | E24: Oficial de cumplimiento | F24: Como oficial de cumplimiento, quiero cotejar clientes y transacciones contra listas restrictivas (OFAC, World-Check, PEP) para cumplir leyes antilavado. | G24: CA1: El sistema debe cotejar a cada cliente contra listas restrictivas (OFAC, World-Check, PEP) durante el onboarding. CA2: El sistema debe validar las transacciones en tiempo real contra las mismas listas restrictivas. CA3: El sistema debe generar un reporte de operación sospechosa (ROS) cuando se detecte una coincidencia relevante. CA4: El sistema debe registrar el resultado de cada validación para su posterior auditoría. | H24: Must | I24: 8 | J24: Sí
A25: HU22 | C25: Sprint 4 | D25: Notificaciones de Seguridad Multicanal | E25: Cliente | F25: Como cliente, quiero recibir alertas push y correos instantáneos por cada transacción o login biométrico para detectar cualquier actividad no autorizada. | G25: CA1: El sistema debe enviar una alerta push inmediata por cada transacción o inicio de sesión biométrico. CA2: El sistema debe enviar un correo electrónico con el mismo detalle de la alerta como respaldo. CA3: El sistema debe incluir en la alerta el dispositivo, hora y ubicación aproximada del evento. CA4: El sistema debe permitir al cliente reportar una actividad como no reconocida directamente desde la notificación. | H25: Should | I25: 3 | J25: Sí
A26: HU23 | C26: Sprint 4 | D26: Bitácora de Auditoría Inalterable (Audit Log) | E26: Auditor | F26: Como auditor, quiero consultar registros inalterables y con marca de tiempo de todos los cambios administrativos y verificaciones faciales para respaldar auditorías. | G26: CA1: El sistema debe registrar todo cambio administrativo y verificación facial en un log de solo lectura (append-only). CA2: El sistema debe aplicar un hash criptográfico a cada registro para garantizar su no repudio. CA3: El sistema debe permitir al auditor consultar los registros filtrando por fecha, usuario o tipo de evento. CA4: El sistema debe impedir la modificación o eliminación de cualquier registro ya almacenado. | H26: Could | I26: 5 | J26: No
A27: HU24 | B27: Épica 7 – Productos Avanzados | C27: Sprint 4 | D27: Cuentas Multidivisa y Meta de Ahorro Automático | E27: Cliente | F27: Como cliente, quiero aperturar bolsillos de ahorro y cuentas en USD/EUR para organizar mis metas con reglas de redondeo automático. | G27: CA1: El sistema debe permitir aperturar bolsillos de ahorro y cuentas en USD/EUR desde la app. CA2: El sistema debe permitir configurar reglas de redondeo automático hacia una meta de ahorro. CA3: El sistema debe calcular y acreditar automáticamente los rendimientos generados por cada bolsillo. CA4: El sistema debe permitir traspasos de fondos entre bolsillos y cuentas del mismo cliente. | H27: Should | I27: 5 | J27: Sí
A28: HU25 | C28: Sprint 4 | D28: Módulo de Cambio de Divisas Preferencial | E28: Cliente | F28: Como cliente, quiero comprar y vender divisas con tipo de cambio competitivo en tiempo real para optimizar mi dinero. | G28: CA1: El sistema debe mostrar una cotización de cambio en tiempo real congelada por 30 segundos antes de confirmar. CA2: El sistema debe aplicar un spread dinámico según el volumen de la operación. CA3: El sistema debe ejecutar la compra o venta de divisas de forma inmediata al confirmar la cotización vigente. CA4: El sistema debe rechazar la operación si la cotización congelada expiró antes de la confirmación. | H28: Should | I28: 8 | J28: Sí
A29: HU26 | C29: Sprint 4 | D29: Distribución Automática de Ingresos y Nómina | E29: Cliente | F29: Como cliente, quiero programar la distribución automática de mi sueldo en porcentajes apenas ingrese mi pago para presupuestar sin esfuerzo. | G29: CA1: El sistema debe permitir programar reglas de distribución automática por porcentaje sobre los ingresos recibidos. CA2: El sistema debe ejecutar la dispersión automática hacia facturas, ahorros e inversión al recibir un abono masivo. CA3: El sistema debe validar que la suma de los porcentajes configurados no exceda el 100%. CA4: El sistema debe notificar al cliente el detalle de cada distribución ejecutada. | H29: Could | I29: 8 | J29: No
I35: =SUM(I4:I29)-13 -> 160

Sheet Criterios Aceptacion
A1: Criterios de Aceptación — Sistema Bancario (Formato Gherkin: Dado / Cuando / Entonces)
A3: ID HU | B3: Área | C3: Requerimiento no funcional | D3: Criterio | E3: Dado | F3: Cuando | G3: Entonces | H3: Resultado esperado
A4: HU01 | B4: Registro y KYC Biométrico | C4: Seguridad / Rendimiento | D4: CA-01 | E4: Dado que el cliente escanea su documento de identidad físico | F4: Cuando el sistema procesa la captura mediante OCR | G4: Entonces se extraen los datos personales con una precisión mínima del 95% y se valida su vigencia | H4: Captura OCR válida
C5: Seguridad | D5: CA-02 | E5: Dado que los datos del documento fueron reconocidos | F5: Cuando el cliente realiza el escaneo facial en vivo | G5: Entonces el sistema ejecuta la prueba de vida (liveness detection) descartando intentos con fotos, videos o máscaras | H5: Liveness verificado
C6: Integridad / Confiabilidad | D6: CA-03 | E6: Dado que la prueba de vida es exitosa | F6: Cuando se contrasta el rostro con la foto del documento y la base oficial (RENIEC) | G6: Entonces se aprueba la coincidencia únicamente si el match supera el umbral de confianza configurado | H6: Match oficial confirmado
C7: Usabilidad / Trazabilidad | D7: CA-04 | E7: Dado que la validación biométrica no supera el umbral requerido | F7: Cuando se detecta la inconsistencia de identidad | G7: Entonces el sistema informa el motivo, permite reintentos limitados y deriva el caso a revisión manual si persiste | H7: Manejo de excepción KYC
A8: HU02 | B8: Verificación y Activación | C8: Seguridad | D8: CA-01 | E8: Dado que el cliente completó exitosamente la validación KYC | F8: Cuando el sistema procesa el alta de la solicitud | G8: Entonces se envía un código OTP de un solo uso de forma inmediata al correo y número celular registrados | H8: OTP generado y enviado
C9: Seguridad | D9: CA-02 | E9: Dado que el cliente recibe el código OTP | F9: Cuando lo ingresa dentro de los 10 minutos de vigencia | G9: Entonces el sistema valida el código, activa la cuenta digital y actualiza su estado a activa | H9: Cuenta activada
C10: Disponibilidad / Seguridad | D10: CA-03 | E10: Dado que el cliente no recibió el código o expiró | F10: Cuando solicita el reenvío del OTP | G10: Entonces el sistema permite hasta 3 solicitudes respetando un intervalo mínimo de espera entre envíos | H10: Reenvío de OTP controlado
C11: Usabilidad | D11: CA-04 | E11: Dado que la cuenta ha sido activada con éxito | F11: Cuando finaliza la pantalla de activación | G11: Entonces el sistema confirma al cliente y lo habilita para iniciar sesión con sus credenciales biométricas | H11: Acceso inicial habilitado
A12: HU03 | B12: Seguridad y Autenticación | C12: Rendimiento | D12: CA-01 | E12: Dado que el cliente tiene el reconocimiento biométrico activado | F12: Cuando abre la aplicación e inicia el escaneo facial | G12: Entonces el sistema valida la biometría y permite el acceso en menos de 1.5 segundos | H12: Acceso biométrico rápido
C13: Disponibilidad | D13: CA-02 | E13: Dado que las condiciones de luz impiden el match facial | F13: Cuando el reconocimiento biométrico no reconoce el rostro | G13: Entonces el sistema habilita el método secundario solicitando huella digital o PIN de contingencia | H13: Contingencia MFA
C14: Seguridad | D14: CA-03 | E14: Dado que se registran 5 intentos fallidos consecutivos de autenticación | F14: Cuando se procesa el quinto intento fallido | G14: Entonces la cuenta se bloquea temporalmente y se envía una notificación de alerta al cliente | H14: Ataque mitigado
C15: Seguridad | D15: CA-04 | E15: Dado que la aplicación permanece en segundo plano o sin interacción | F15: Cuando transcurre el tiempo configurado de inactividad (ej. 3 min) | G15: Entonces el sistema finaliza la sesión activa y solicita autenticación para reingresar | H15: Sesión protegida
A16: HU04 | B16: Recuperación de Cuenta | C16: Usabilidad | D16: CA-01 | E16: Dado que el usuario olvidó sus credenciales o tiene el acceso bloqueado | F16: Cuando selecciona 'Recuperar cuenta' desde la pantalla de login | G16: Entonces el sistema inicia el flujo solicitando únicamente su documento de identidad sin requerir clave previa | H16: Inicio autónomo
C17: Seguridad | D17: CA-02 | E17: Dado que el número de documento pertenece a un cliente activo | F17: Cuando el usuario efectúa el escaneo facial de prueba de vida | G17: Entonces el sistema re-valida el rostro contra el patrón biométrico original almacenado | H17: Re-validación biométrica
C18: Seguridad / Integridad | D18: CA-03 | E18: Dado que la re-validación biométrica resulta exitosa | F18: Cuando el usuario define su nueva contraseña o PIN | G18: Entonces el sistema actualiza las credenciales de inmediato en el repositorio seguro | H18: Restablecimiento de clave
C19: Auditoría / Seguridad | D19: CA-04 | E19: Dado que las credenciales han sido cambiadas | F19: Cuando concluye el proceso de restablecimiento | G19: Entonces el sistema notifica por push y correo detallando fecha, hora y dispositivo, revocando sesiones previas | H19: Notificación y revocación
A20: HU05 | B20: Cuentas y Saldos | C20: Usabilidad | D20: CA-01 | E20: Dado que el cliente tiene cuentas asociadas | F20: Cuando ingresa al dashboard principal | G20: Entonces se muestran todas sus cuentas con tipo de producto, número enmascarado y moneda | H20: Vista consolidada
C21: Integridad de datos | D21: CA-02 | E21: Dado que una cuenta posee transacciones retenidas | F21: Cuando el cliente consulta el detalle de la cuenta | G21: Entonces el sistema desglosa claramente el saldo contable respecto al saldo disponible neto | H21: Diferenciación de saldo
C22: Rendimiento | D22: CA-03 | E22: Dado que una cuenta registra nuevos movimientos | F22: Cuando el cliente selecciona la cuenta | G22: Entonces el listado de movimientos históricos y recientes se actualiza y muestra en tiempo real | H22: Movimientos en tiempo real
C23: Portabilidad | D23: CA-04 | E23: Dado que el usuario necesita sus transacciones para trámites | F23: Cuando presiona 'Exportar movimientos' | G23: Entonces el sistema genera y descarga un archivo estructurado en PDF o Excel con el reporte filtrado | H23: Reporte descargable
A24: HU06 | B24: Transferencias | C24: Rendimiento | D24: CA-01 | E24: Dado que ambas cuentas pertenecen al mismo cliente | F24: Cuando ingresa un monto válido y confirma la operación | G24: Entonces el débito y crédito se registran de forma inmediata y sin comisión entre cuentas propias | H24: Movimiento interno inmediato
C25: Integridad | D25: CA-02 | E25: Dado que el destinatario es de otra entidad financiera | F25: Cuando ingresa el código CCI y consulta la cuenta | G25: Entonces el sistema valida la titularidad antes de debitar y permite la transferencia interbancaria | H25: Validación CCI
C26: Seguridad / Integridad | D26: CA-03 | E26: Dado que el saldo disponible en la cuenta origen es menor al monto solicitado | F26: Cuando el cliente intenta confirmar la transferencia | G26: Entonces el sistema rechaza la operación sin modificar los saldos contables | H26: Saldo protegido
C27: Trazabilidad | D27: CA-04 | E27: Dado que la transferencia se ejecuta con éxito | F27: Cuando culmina la transacción en el sistema | G27: Entonces se genera un comprobante descargable con fecha, hora, monto, cuentas y número de operación único | H27: Comprobante oficial
A28: HU08 | B28: Seguridad Transaccional | C28: Seguridad | D28: CA-01 | E28: Dado que el monto de una transferencia supera el umbral parametrizado de seguridad | F28: Cuando el cliente presiona continuar para transferir | G28: Entonces el sistema exige obligatoriamente un escaneo facial biométrico para autorizar el cargo | H28: Exigencia biométrica
C29: Seguridad | D29: CA-02 | E29: Dado que la validación facial está pendiente | F29: Cuando no se ha completado el match satisfactoriamente | G29: Entonces el sistema restringe el envío y mantiene retenida la transacción sin ejecutar el débito | H29: Bloqueo preventivo
C30: Regulatorio / Riesgos | D30: CA-03 | E30: Dado que el cliente tiene un perfil de riesgo específico | F30: Cuando intenta realizar transacciones acumuladas en el día | G30: Entonces el sistema aplica los límites máximos diarios parametrizados para dicho perfil | H30: Límites aplicados
C31: Auditoría | D31: CA-04 | E31: Dado que un intento de autorización biométrica resulta fallido o sospechoso | F31: Cuando el sistema detecta la anomalía | G31: Entonces registra el evento de seguridad en auditoría y envía una alerta de advertencia al cliente | H31: Alerta de fraude
A32: HU07 | B32: Beneficiarios | C32: Usabilidad | D32: CA-01 | E32: Dado que una transferencia a un tercero concluyó exitosamente | F32: Cuando el cliente pulsa 'Guardar en frecuentes' | G32: Entonces el sistema almacena el contacto con alias personalizado, foto y datos bancarios asociados | H32: Beneficiario guardado
C33: Usabilidad | D33: CA-02 | E33: Dado que el cliente tiene múltiples contactos guardados | F33: Cuando escribe en el buscador de la agenda | G33: Entonces el sistema filtra en tiempo real por alias o nombre para una selección rápida | H33: Búsqueda predictiva
C34: Seguridad | D34: CA-03 | E34: Dado que el cliente configura su agenda de contactos | F34: Cuando establece un límite de monto pre-aprobado para un beneficiario frecuente | G34: Entonces el sistema permite transferencias ágiles hasta ese tope sin solicitar factores de seguridad adicionales | H34: Tope pre-aprobado
C35: Mantenibilidad | D35: CA-04 | E35: Dado que un beneficiario frecuente cambia de datos o ya no se requiere | F35: Cuando el cliente selecciona editar o eliminar el contacto | G35: Entonces el sistema actualiza o remueve el registro tras una confirmación de seguridad | H35: Gestión de agenda
A36: HU09 | B36: Créditos Digitales | C36: Precisión / Rendimiento | D36: CA-01 | E36: Dado que el usuario accede al simulador de créditos | F36: Cuando ingresa el monto, plazo y tasa de interés TCEA | G36: Entonces el sistema calcula y muestra instantáneamente la cuota mensual estimada | H36: Cálculo de cuota
C37: Transparencia | D37: CA-02 | E37: Dado que se calculó la cuota mensual | F37: Cuando el usuario despliega la tabla de pagos provisional | G37: Entonces el sistema detalla la amortización de capital, intereses devengados y fechas probables de pago | H37: Cronograma simulado
C38: Regulatorio | D38: CA-03 | E38: Dado que el préstamo requiere cobertura de desgravamen | F38: Cuando el cliente activa o desactiva la opción de seguro | G38: Entonces el sistema recalcula la cuota incorporando la prima correspondiente de manera transparente | H38: Seguro desgravamen
C39: Portabilidad | D39: CA-04 | E39: Dado que la simulación cumple con las expectativas del usuario | F39: Cuando presiona 'Descargar simulación' | G39: Entonces el sistema exporta un archivo PDF con las condiciones informativas sin carácter vinculante | H39: Cotización descargable
A40: HU10 | B40: Evaluación Crediticia | C40: Legal / Cumplimiento | D40: CA-01 | E40: Dado que el cliente completa los datos de la solicitud crediticia | F40: Cuando acepta explícitamente el tratamiento de datos y consulta en centrales de riesgo | G40: Entonces el sistema crea un expediente formal con ID único y estado 'En evaluación' | H40: Solicitud registrada
C41: Integridad | D41: CA-02 | E41: Dado que un campo obligatorio del formulario se encuentra vacío o con formato erróneo | F41: Cuando el usuario pulsa enviar solicitud | G41: Entonces el sistema indica claramente el error y no remite la evaluación al motor de crédito | H41: Validación de campos
C42: Rendimiento | D42: CA-03 | E42: Dado que la solicitud cuenta con todos los requisitos completos | F42: Cuando el motor de riesgos y scoring interno procesa la consulta | G42: Entonces el sistema emite el dictamen de calificación en menos de 2 minutos | H42: Dictamen automatizado
C43: Usabilidad / Trazabilidad | D43: CA-04 | E43: Dado que la evaluación ha sido resuelta | F43: Cuando concluye el análisis | G43: Entonces el sistema notifica al cliente con un estado claro (Aprobado, Rechazado o En Revisión) y guarda el dictamen | H43: Estado visible
A44: HU11 | B44: Legalización y Contratos | C44: Transparencia | D44: CA-01 | E44: Dado que el crédito fue aprobado favorablemente | F44: Cuando el cliente accede al paso de formalización | G44: Entonces el sistema presenta el contrato, pagaré digital y hoja resumen para su completa lectura | H44: Visualización contractual
C45: Seguridad / Legal | D45: CA-02 | E45: Dado que el cliente revisó las condiciones del préstamo | F45: Cuando pulsa 'Firmar contrato' | G45: Entonces el sistema captura el rostro mediante biometría facial como mecanismo de consentimiento explícito | H45: Consentimiento biométrico
C46: Integridad / No repudio | D46: CA-03 | E46: Dado que la identidad facial fue validada | F46: Cuando se firma el contrato electrónicamente | G46: Entonces se estampa un certificado digital sellado criptográficamente vinculando el token facial | H46: Firma digital certificada
C47: Cumplimiento | D47: CA-04 | E47: Dado que el documento quedó formalmente legalizado | F47: Cuando finaliza la firma | G47: Entonces el sistema remite una copia certificada del contrato y pagaré al correo del cliente | H47: Copia legalizada remitida
A48: HU12 | B48: Desembolsos y Cobranzas | C48: Rendimiento | D48: CA-01 | E48: Dado que el contrato crediticio se encuentra firmado | F48: Cuando se procesa la orden de abono | G48: Entonces el monto aprobado se acredita en tiempo real en la cuenta bancaria seleccionada por el cliente | H48: Desembolso inmediato
C49: Trazabilidad | D49: CA-02 | E49: Dado que los fondos fueron acreditados | F49: Cuando se confirma el desembolso | G49: Entonces el sistema genera el cronograma de cuotas definitivo indicando montos, fechas y capital amortizado | H49: Cronograma definitivo
C50: Disponibilidad | D50: CA-03 | E50: Dado que el cliente prefiere pagar automáticamente | F50: Cuando activa la opción de débito automático | G50: Entonces el sistema programa el cobro automático de la cuota en la fecha de vencimiento contra la cuenta designada | H50: Débito automático activo
C51: Notificaciones | D51: CA-04 | E51: Dado que se acerca la fecha de pago de una cuota | F51: Cuando restan 3 días para el vencimiento | G51: Entonces el sistema envía una alerta push y correo recordando el monto exacto por cancelar | H51: Recordatorio de pago
A52: HU13 | B52: Billetera Digital | C52: Usabilidad | D52: CA-01 | E52: Dado que el cliente tiene cuentas o tarjetas activas | F52: Cuando accede al módulo de billetera digital | G52: Entonces puede asociar su tarjeta de débito o cuenta preferida como fuente de fondos | H52: Vinculación de cuenta
C53: Rendimiento | D53: CA-02 | E53: Dado que la cuenta está vinculada a la billetera | F53: Cuando el usuario paga en comercios presenciales autorizados | G53: Entonces se efectúa el pago express sin requerir digitar claves bancarias tradicionales | H53: Pago express sin clave
C54: Interoperabilidad | D54: CA-03 | E54: Dado que el pago se dirige a redes de pago interbancarias de la industria | F54: Cuando se confirma la transacción | G54: Entonces el sistema liquida la operación de manera compatible y transparente con otras plataformas | H54: Interoperabilidad completa
C55: Seguridad | D55: CA-04 | E55: Dado que se realizan pagos rápidos continuos | F55: Cuando el monto acumulado del día alcanza el tope máximo express | G55: Entonces el sistema exige validación de seguridad reforzada antes de autorizar nuevos consumos | H55: Límite diario express
A56: HU14 | B56: Cobros QR | C56: Usabilidad | D56: CA-01 | E56: Dado que un comercio requiere cobrar una venta | F56: Cuando ingresa el monto específico y el concepto | G56: Entonces el sistema genera un código QR dinámico de alta definición en la pantalla | H56: QR de cobro generado
C57: Seguridad | D57: CA-02 | E57: Dado que se ha generado un QR dinámico | F57: Cuando expira el tiempo configurado de vigencia (ej. 5 min) | G57: Entonces el código QR caduca automáticamente e impide cualquier intento de pago posterior | H57: Caducidad de QR
C58: Interoperabilidad | D58: CA-03 | E58: Dado que el cliente comprador utiliza una billetera de otra entidad | F58: Cuando escanea el QR del comercio | G58: Entonces el sistema procesa el abono respetando el estándar interoperable nacional | H58: QR interoperable
C59: Rendimiento / Notificaciones | D59: CA-04 | E59: Dado que el cliente confirma el pago del QR | F59: Cuando la red autoriza la transacción | G59: Entonces la aplicación del comercio emite una alerta visual y push confirmando el abono en el acto | H59: Notificación de abono
A60: HU15 | B60: Pagos QR | C60: Rendimiento | D60: CA-01 | E60: Dado que el cliente abre el escáner QR de la app | F60: Cuando apunta la cámara a un código QR válido | G60: Entonces el lector decodifica y muestra el nombre del comercio y monto a pagar en menos de 1 segundo | H60: Lectura QR inmediata
C61: Usabilidad | D61: CA-02 | E61: Dado que el monto se ubica dentro del límite base | F61: Cuando el usuario revisa los datos y presiona pagar | G61: Entonces la operación se procesa en un solo toque debitando de la cuenta seleccionada | H61: Pago en un toque
C62: Seguridad | D62: CA-03 | E62: Dado que el monto por pagar excede el límite de pago rápido | F62: Cuando el usuario intenta autorizar la operación | G62: Entonces el sistema solicita obligatoriamente validación biométrica facial o huella | H62: Autorización biométrica QR
C63: Seguridad / Integridad | D63: CA-04 | E63: Dado que el código QR leído se encuentra vencido, corrupto o manipulado | F63: Cuando el sistema valida la firma del QR | G63: Entonces rechaza inmediatamente el cobro sin descontar fondos y alerta al usuario | H63: QR protegido y auditado
A64: HU16 | B64: Servicios y Recargas | C64: Usabilidad | D64: CA-01 | E64: Dado que el usuario accede al módulo de servicios | F64: Cuando ingresa el nombre de la empresa prestadora o servicio | G64: Entonces el sistema localiza la empresa y muestra los suministros guardados o formulario de consulta | H64: Búsqueda de servicio
C65: Disponibilidad | D65: CA-02 | E65: Dado que el usuario desea recargar saldo a un número telefónico | F65: Cuando elige el operador, número y monto | G65: Entonces el sistema ejecuta la recarga móvil en tiempo real y notifica el abono | H65: Recarga telefónica
C66: Usabilidad | D66: CA-03 | E66: Dado que el cliente tiene servicios frecuentes agregados | F66: Cuando se aproxima la fecha de corte o vencimiento de la factura | G66: Entonces el sistema envía recordatorios automáticos indicando monto exigible | H66: Recordatorio de vencimiento
C67: Trazabilidad | D67: CA-04 | E67: Dado que el pago del recibo fue completado | F67: Cuando concluye el proceso | G67: Entonces el sistema emite un comprobante estructurado con el número de transacción oficial de la empresa | H67: Comprobante estructurado
A68: HU17 | B68: Core Transaccional | C68: Integridad / Consistencia | D68: CA-01 | E68: Dado que una transacción es enviada al core bancario | F68: Cuando el motor inicia la verificación previa | G68: Entonces se valida el saldo disponible en tiempo real impidiendo operaciones en descubierto | H68: Control de saldo estricto
C69: Concurrencia / ACID | D69: CA-02 | E69: Dado que se procesa una orden de pago | F69: Cuando la transacción entra en fase de compensación | G69: Entonces los fondos son bloqueados temporalmente para evitar sobregiros simultáneos | H69: Bloqueo preventivo de fondos
C70: Idempotencia | D70: CA-03 | E70: Dado que llega una solicitud duplicada por reintento de red | F70: Cuando se detecta un identificador de transacción idéntico ya procesado | G70: Entonces el sistema devuelve el resultado original sin cobrar dos veces | H70: Prevención de doble gasto
C71: Rendimiento | D71: CA-04 | E71: Dado que el core opera bajo condiciones estándar de demanda | F71: Cuando procesa el ciclo transaccional | G71: Entonces el tiempo de respuesta total no excede los 200 milisegundos cumpliendo el SLA | H71: SLA transaccional < 200ms
A72: HU18 | B72: Contabilidad Core | C72: Integridad contable | D72: CA-01 | E72: Dado que una transacción financiera fue autorizada | F72: Cuando se registra en el libro mayor | G72: Entonces el débito y el crédito se asientan atómicamente respetando la partida doble | H72: Partida doble balanceada
C73: Trazabilidad / No repudio | D73: CA-02 | E73: Dado que se genera un nuevo asiento contable | F73: Cuando se confirma en la base de datos | G73: Entonces el sistema le asigna un identificador universal único (UUID) inalterable | H73: UUID contable asignado
C74: Integridad | D74: CA-03 | E74: Dado que ocurre un error o caída técnica durante el registro de uno de los asientos | F74: Cuando el sistema detecta la falla parcial | G74: Entonces ejecuta un rollback automático y ningún asiento queda aplicado de forma parcial | H74: Atomicidad contable
C75: Conformidad financiera | D75: CA-04 | E75: Dado que concluye la jornada operativa diaria | F75: Cuando se dispara el proceso de cierre contable nocturno | G75: Entonces el sistema verifica que la sumatoria de débitos y créditos sea idéntica emitiendo el balance diario | H75: Cierre contable cuadrado
A76: HU19 | B76: Operaciones y Compensación | C76: Integridad | D76: CA-01 | E76: Dado que se reciben archivos de compensación (clearing) de las redes externas | F76: Cuando el sistema procesa el lote al cierre | G76: Entonces extrae y valida la totalidad de los registros de compensación automáticamente | H76: Clearing procesado
C77: Confiabilidad | D77: CA-02 | E77: Dado que existen registros bancarios internos y de las redes de pago | F77: Cuando se ejecuta la conciliación automática | G77: Entonces el sistema contrasta los montos y detecta cualquier descuadre o transacción huérfana | H77: Cruce y conciliación
C78: Trazabilidad | D78: CA-03 | E78: Dado que se hallaron inconsistencias en la liquidación | F78: Cuando culmina la conciliación | G78: Entonces el sistema emite un reporte pormenorizado de discrepancias para el analista de operaciones | H78: Reporte de diferencias
C79: Mantenibilidad | D79: CA-04 | E79: Dado que una discrepancia requiere ajuste formal | F79: Cuando el analista revisa el reporte | G79: Entonces el sistema provee un flujo de reclamos y resolución para regularizar los saldos | H79: Flujo de reclamos operativo
A80: HU20 | B80: Prevención de Fraude | C80: Seguridad | D80: CA-01 | E80: Dado que se realiza un intento de login con patrones faciales sintéticos | F80: Cuando el motor antifraude analiza la muestra | G80: Entonces detecta ataques de inyección, deepfakes o spoofing emitiendo una alerta crítica | H80: Detección de spoofing facial
C81: Seguridad / IA | D81: CA-02 | E81: Dado que se efectúa una transacción con geolocalización o monto atípico | F81: Cuando el motor coteja el comportamiento habitual del cliente | G81: Entonces clasifica el evento como transacción de alto riesgo | H81: Anomalía de comportamiento
C82: Seguridad | D82: CA-03 | E82: Dado que una transacción es calificada con puntaje de riesgo crítico | F82: Cuando se intenta cursar la operación | G82: Entonces el sistema aplica un bloqueo preventivo antes de liberar los fondos | H82: Bloqueo preventivo de fraude
C83: Usabilidad / Monitoreo | D83: CA-04 | E83: Dado que se suscitan alertas de riesgo en tiempo real | F83: Cuando el analista de fraude consulta el sistema | G83: Entonces las alertas se consolidan en un tablero interactivo para gestión y desbloqueo | H83: Tablero de monitoreo antifraude
A84: HU21 | B84: Cumplimiento y PLAFT | C84: Regulatorio | D84: CA-01 | E84: Dado que una persona inicia el proceso de onboarding | F84: Cuando el sistema registra sus datos de identidad | G84: Entonces coteja automáticamente contra listas vinculantes (OFAC, World-Check, PEP) en tiempo real | H84: Matching en onboarding
C85: Regulatorio | D85: CA-02 | E85: Dado que se intenta ejecutar una transacción bancaria | F85: Cuando los datos del emisor o receptor entran al motor de filtrado | G85: Entonces se valida que ninguna de las partes figure en listas de sanciones internacionales | H85: Filtrado transaccional
C86: Legal / Compliance | D86: CA-03 | E86: Dado que se detecta coincidencia confirmada con una lista restrictiva | F86: Cuando salta la alerta de coincidencia | G86: Entonces el sistema genera automáticamente un Reporte de Operación Sospechosa (ROS) para el oficial de cumplimiento | H86: Generación de ROS
C87: Auditoría | D87: CA-04 | E87: Dado que se ejecutaron análisis de cumplimiento | F87: Cuando concluye cada validación | G87: Entonces el sistema archiva una bitácora inalterable con la fecha, resultado y lista consultada para fines regulatorios | H87: Auditoría PLAFT
A88: HU22 | B88: Alertas y Notificaciones | C88: Rendimiento | D88: CA-01 | E88: Dado que se procesa cualquier movimiento o acceso a la cuenta | F88: Cuando se confirma la transacción en el servidor | G88: Entonces se dispara una notificación push de forma inmediata al dispositivo móvil del cliente | H88: Push de seguridad instantáneo
C89: Disponibilidad | D89: CA-02 | E89: Dado que se efectuó un evento de seguridad o cargo financiero | F89: Cuando se envía la notificación push | G89: Entonces el sistema remite en paralelo un correo electrónico con los datos de respaldo de la operación | H89: Alerta por correo electrónico
C90: Transparencia / Seguridad | D90: CA-03 | E90: Dado que se envía una alerta al cliente | F90: Cuando el usuario revisa el contenido | G90: Entonces se indica el dispositivo utilizado, hora exacta, monto y ubicación aproximada | H90: Detalle de seguridad
C91: Seguridad | D91: CA-04 | E91: Dado que el cliente recibe una notificación de un movimiento que no efectuó | F91: Cuando pulsa el botón 'No reconozco esta operación' en la alerta | G91: Entonces el sistema bloquea inmediatamente los canales digitales y contacta a soporte de seguridad | H91: Reporte inmediato de fraude
A92: HU23 | B92: Auditoría del Sistema | C92: Seguridad / Integridad | D92: CA-01 | E92: Dado que un administrador o usuario realiza un cambio sensible o verificación biométrica | F92: Cuando la acción es procesada | G92: Entonces se registra en una bitácora de auditoría estructurada de solo lectura (append-only) | H92: Log append-only
C93: No repudio | D93: CA-02 | E93: Dado que se crea un registro de evento en la bitácora | F93: Cuando se guarda en el log | G93: Entonces se genera un hash criptográfico enlazado que garantiza la inmutabilidad y autenticidad del registro | H93: Sellado criptográfico de log
C94: Usabilidad / Trazabilidad | D94: CA-03 | E94: Dado que el auditor requiere examinar eventos históricos | F94: Cuando filtra por rango de fechas, usuario o tipo de transacción | G94: Entonces el sistema despliega las trazas detalladas con sus sellos de tiempo verificables | H94: Consulta de auditoría filtrada
C95: Seguridad estricta | D95: CA-04 | E95: Dado que los registros fueron almacenados en la base de auditoría | F95: Cuando cualquier usuario (incluso con permisos de superadministrador) intenta modificarlos o eliminarlos | G95: Entonces el sistema deniega la acción y emite una alerta crítica de intento de manipulación | H95: Inmutabilidad garantizada
A96: HU24 | B96: Ahorro y Multidivisa | C96: Usabilidad | D96: CA-01 | E96: Dado que el cliente posee una cuenta en moneda nacional | F96: Cuando solicita crear un bolsillo de ahorro o cuenta en USD/EUR desde la app | G96: Entonces el sistema habilita el producto en moneda extranjera de manera digital e inmediata | H96: Apertura multidivisa
C97: Usabilidad / Funcional | D97: CA-02 | E97: Dado que el cliente establece una meta de ahorro | F97: Cuando efectúa consumos con su tarjeta | G97: Entonces el sistema redondea los pagos al sol superior y transfiere el excedente automáticamente al bolsillo de ahorro | H97: Redondeo automático
C98: Confiabilidad | D98: CA-03 | E98: Dado que el dinero permanece en el bolsillo de ahorro remunerado | F98: Cuando se cumple el periodo de cálculo de intereses | G98: Entonces el sistema computa y abona los rendimientos generados según la tasa pactada | H98: Abono de rendimientos
C99: Disponibilidad | D99: CA-04 | E99: Dado que el cliente necesita disponer de sus fondos de ahorro | F99: Cuando transfiere dinero desde el bolsillo hacia su cuenta principal | G99: Entonces el traslado se aplica inmediatamente sin penalidad ni comisiones | H99: Traspaso libre entre bolsillos
A100: HU25 | B100: Cambio de Divisas | C100: Precisión / Rendimiento | D100: CA-01 | E100: Dado que el usuario desea comprar o vender moneda extranjera | F100: Cuando solicita una cotización en pantalla | G100: Entonces el sistema fija y congela el tipo de cambio preferencial garantizado durante 30 segundos | H100: Tipo de cambio congelado
C101: Financiero | D101: CA-02 | E101: Dado que la operación involucra montos de divisa elevados | F101: Cuando el sistema calcula el precio de compra o venta | G101: Entonces aplica un spread dinámico más competitivo proporcional al volumen transaccionado | H101: Spread dinámico por volumen
...

Sheet Requerimientos Func-NoFunc
A1: Requerimientos Funcionales y No Funcionales por Historia de Usuario
A3: ID | B3: Épica | C3: Historia de Usuario | D3: Requerimientos Funcionales (RF) | E3: Requerimientos No Funcionales (RNF)
A4: HU01 | B4: Épica 1 – Identidad, Biometría y KYC | C4: Como cliente nuevo, quiero registrarme escaneando mi documento de identidad y validando mi rostro con Liveness Detection para aperturar mi cuenta digital de forma segura sin ir a una agencia. | D4: RF1: Capturar el documento de identidad (DNI/CE) mediante cámara y extraer los datos por OCR. RF2: Ejecutar prueba de vida (liveness detection) y comparar el rostro contra el documento y la base RENIEC. RF3: Crear automáticamente el usuario y la cuenta digital tras la validación exitosa del KYC. | E4: RNF1: Precisión de OCR ≥95% y de match facial ≥98% para minimizar falsos positivos/negativos. RNF2: El proceso completo de KYC no debe superar 60 segundos en condiciones normales de red. RNF3: Los datos biométricos y documentales deben cifrarse en tránsito y en reposo (TLS 1.2+/AES-256).
A5: HU27 | C5: Como cliente nuevo, quiero confirmar mi registro mediante un código de verificación enviado a mi correo o celular para activar mi cuenta digital antes de iniciar sesión por primera vez. | D5: RF1: Enviar un código OTP al correo o celular registrado al completar el KYC. RF2: Validar el OTP ingresado y activar la cuenta si es correcto y vigente. RF3: Permitir el reenvío del OTP con límite de intentos y tiempo de espera entre solicitudes. | E5: RNF1: El OTP debe expirar en un máximo de 10 minutos desde su generación. RNF2: El envío del OTP debe tener un SLA de entrega menor a 5 segundos. RNF3: El código debe ser de un solo uso y no reutilizable tras su validación o expiración.
A6: HU02 | C6: Como cliente, quiero ingresar a la banca móvil mediante reconocimiento facial rápido o biométricos secundarios (Huella/PIN) para acceder sin recordar contraseñas complejas. | D6: RF1: Permitir el inicio de sesión mediante reconocimiento facial como método principal. RF2: Ofrecer huella digital o PIN como método alternativo. RF3: Bloquear temporalmente la cuenta tras intentos fallidos consecutivos y cerrar sesión por inactividad. | E6: RNF1: La validación biométrica debe completarse en menos de 1.5 segundos. RNF2: El módulo de autenticación debe tener una disponibilidad mínima del 99.9%. RNF3: Los bloqueos por intentos fallidos deben registrarse sin exponer información sensible del cliente.
A7: HU04 | C7: Como cliente, quiero recuperar mi acceso o desbloquear mi usuario mediante re-validación de biometría facial para restablecer mis credenciales de forma autónoma. | D7: RF1: Permitir solicitar la recuperación de acceso desde el login sin contraseña previa. RF2: Re-validar el rostro del cliente contra el patrón biométrico almacenado. RF3: Permitir el restablecimiento de credenciales solo tras una validación facial exitosa. | E7: RNF1: El umbral de coincidencia facial para recuperación debe ser más estricto que el del login habitual. RNF2: El cambio de credenciales debe notificarse por un canal distinto en menos de 1 minuto. RNF3: Todo intento de recuperación debe quedar auditado con fecha, dispositivo y resultado.
A8: HU05 | B8: Épica 2 – Cuentas y Transacciones | C8: Como cliente, quiero consultar saldos disponibles, fondos retenidos y movimientos en tiempo real para mantener control de mi patrimonio. | D8: RF1: Mostrar todas las cuentas del cliente con tipo, número enmascarado y saldo disponible. RF2: Desglosar saldo contable, saldo disponible y fondos retenidos por cuenta. RF3: Permitir exportar el detalle de movimientos en PDF o Excel. | E8: RNF1: La consulta de saldos y movimientos debe responder en menos de 2 segundos. RNF2: El sistema debe soportar consultas concurrentes de miles de clientes sin degradar el tiempo de respuesta. RNF3: El número de cuenta debe mostrarse siempre enmascarado en pantalla.
A9: HU06 | C9: Como cliente, quiero transferir dinero entre mis cuentas y a terceros (mismo banco o interbancarias inmediatas) para mover mis fondos sin comisión oculta. | D9: RF1: Transferir fondos entre cuentas propias de forma inmediata y sin costo. RF2: Realizar transferencias interbancarias mediante CCI/CCE validando al titular antes de confirmar. RF3: Generar comprobante descargable con número de operación. | E9: RNF1: Las transferencias interbancarias deben ejecutarse en menos de 10 segundos. RNF2: El sistema debe garantizar idempotencia para evitar cobros duplicados ante reintentos de red. RNF3: Toda transferencia debe quedar trazada con fecha, hora y usuario para auditoría.
A10: HU08 | C10: Como cliente, quiero confirmar transferencias de alto monto mediante escaneo facial instantáneo para garantizar que nadie transfiera sin mi presencia física, y que el sistema restrinja transacciones según mi perfil de riesgo. | D10: RF1: Solicitar validación facial adicional cuando el monto supere el umbral de seguridad. RF2: Restringir el envío de la transacción hasta validar la biometría. RF3: Registrar y notificar los intentos fallidos de autorización como evento de seguridad. | E10: RNF1: La validación biométrica adicional no debe añadir más de 3 segundos al flujo de pago. RNF2: Los eventos de autorización fallida deben generar alerta en tiempo real al módulo antifraude. RNF3: El umbral de monto para exigir biometría debe ser configurable sin requerir despliegue de código.
A11: HU07 | C11: Como cliente, quiero guardar y agrupar beneficiarios frecuentes con alias y fotos para reducir errores en transferencias recurrentes. | D11: RF1: Registrar un beneficiario con alias, foto y datos de cuenta tras una transferencia exitosa. RF2: Buscar y agrupar beneficiarios guardados por alias o nombre. RF3: Editar o eliminar un beneficiario guardado. | E11: RNF1: La búsqueda de beneficiarios debe responder en menos de 1 segundo con hasta 100 registros. RNF2: Los datos de los beneficiarios deben almacenarse cifrados en la base de datos. RNF3: El límite pre-aprobado por beneficiario solo debe ser editable por el titular autenticado.
A12: HU09 | B12: Épica 3 – Créditos Digitales | C12: Como cliente, quiero simular monto, plazo, tasa TCEA y cuota estimada para evaluar opciones de financiamiento antes de solicitar un crédito. | D12: RF1: Calcular la cuota estimada según monto, plazo y tasa TCEA ingresados. RF2: Generar un cronograma de pagos provisional con capital e intereses. RF3: Permitir incluir opcionalmente un seguro de desgravamen en la simulación. | E12: RNF1: El cálculo de la simulación debe entregarse en menos de 1 segundo. RNF2: Las tasas y fórmulas usadas deben ser configurables por el área de productos sin cambios de código. RNF3: El simulador no debe generar ningún registro crediticio real sobre el cliente.
A13: HU10 | C13: Como cliente, quiero solicitar un préstamo digital y autorizar la consulta en centrales de riesgo para recibir una respuesta de aprobación inmediata. | D13: RF1: Enviar la solicitud de préstamo solo si el cliente autoriza la consulta en centrales de riesgo. RF2: Validar que la solicitud tenga todos los datos obligatorios antes de evaluarla. RF3: Consultar el motor de riesgos y el score interno para generar una pre-calificación. | E13: RNF1: La pre-calificación debe entregarse en un máximo de 5 minutos. RNF2: La integración con centrales de riesgo debe reintentar automáticamente ante caídas del servicio externo. RNF3: El resultado y su justificación deben quedar almacenados para fines regulatorios.
A14: HU11 | C14: Como cliente, quiero firmar digitalmente mi contrato de préstamo validando mi rostro como consentimiento explícito para legalizar la operación sin papeleo. | D14: RF1: Generar el contrato de préstamo con las condiciones aprobadas antes de la firma. RF2: Validar el rostro del cliente como mecanismo de consentimiento explícito. RF3: Enviar el pagaré y contrato sellado al correo del cliente tras la firma. | E14: RNF1: La firma digital debe cumplir estándares de firma electrónica reconocidos (no repudio). RNF2: El documento firmado debe estar disponible para el cliente en menos de 1 minuto. RNF3: El token facial asociado a la firma debe almacenarse cifrado y no reutilizarse en otra transacción.
A15: HU12 | C15: Como cliente, quiero recibir el desembolso directamente en mi cuenta elegida y visualizar mi cronograma de pagos definitivo para abonar mis cuotas a tiempo. | D15: RF1: Acreditar el monto aprobado en la cuenta elegida por el cliente. RF2: Generar el cronograma definitivo de cuotas. RF3: Habilitar el débito automático de las cuotas desde la cuenta elegida. | E15: RNF1: El desembolso debe acreditarse en menos de 30 segundos tras la firma del contrato. RNF2: El sistema debe notificar cada cuota próxima a vencer con al menos 2 días de anticipación. RNF3: El proceso de desembolso debe ser transaccional (todo o nada) para evitar acreditaciones parciales.
A16: HU13 | B16: Épica 4 – Billetera y Pagos QR | C16: Como cliente, quiero vincular una tarjeta/cuenta a mi billetera digital para realizar pagos rápidos sin digitar claves en comercios. | D16: RF1: Vincular una tarjeta o cuenta del cliente a la billetera digital. RF2: Procesar pagos en comercios sin requerir el ingreso de claves adicionales. RF3: Aplicar límites diarios configurables a las operaciones express. | E16: RNF1: El sistema debe ser interoperable con las redes de pago vigentes de la industria. RNF2: El pago con billetera debe completarse en menos de 3 segundos. RNF3: Los datos de la tarjeta/cuenta vinculada deben tokenizarse, sin almacenar el número completo.
A17: HU14 | C17: Como comercio, quiero generar códigos QR con monto y concepto específico para cobrar a mis clientes de forma ágil sin terminal POS físico. | D17: RF1: Generar un código QR con monto y concepto específico para cada cobro. RF2: Permitir configurar la caducidad del código QR generado. RF3: Notificar al comercio mediante push al recibir el abono. | E17: RNF1: El QR debe ser interoperable con otras billeteras y bancos (estándar QR interoperable). RNF2: La generación del QR debe completarse en menos de 1 segundo. RNF3: La notificación de abono debe entregarse en menos de 5 segundos desde la confirmación del pago.
A18: HU15 | C18: Como cliente, quiero escanear un código QR para verificar la información del comercio y pagar en un solo toque. | D18: RF1: Leer el código QR y mostrar el nombre y monto del comercio antes de confirmar el pago. RF2: Permitir completar el pago en un solo toque dentro del límite base. RF3: Rechazar el pago si el QR está vencido o alterado. | E18: RNF1: La lectura y validación del QR debe completarse en menos de 2 segundos. RNF2: El sistema debe validar la integridad del QR (firma/hash) para prevenir manipulación. RNF3: La validación biométrica adicional no debe añadir más de 3 segundos al flujo.
A19: HU16 | C19: Como cliente, quiero pagar servicios básicos (luz, agua, internet) y recargar celulares desde la app para gestionar mis pagos en un solo lugar. | D19: RF1: Buscar un servicio (luz, agua, internet) por número de suministro. RF2: Recargar celulares seleccionando operador y monto desde la app. RF3: Generar comprobante estructurado por cada pago o recarga. | E19: RNF1: La consulta del servicio debe responder en menos de 2 segundos. RNF2: El sistema debe integrar múltiples empresas de servicios y operadores sin cambios estructurales. RNF3: Los recordatorios de vencimiento deben enviarse con al menos 3 días de anticipación.
A20: HU17 | B20: Épica 5 – Motor Transaccional | C20: Como sistema core bancario, quiero procesar transacciones con control de saldos, bloqueo de fondos y prevención de doble gasto para asegurar la consistencia operativa. | D20: RF1: Validar el saldo disponible antes de ejecutar cada transacción. RF2: Bloquear temporalmente los fondos comprometidos hasta la confirmación final. RF3: Prevenir el doble procesamiento ante reintentos o fallas de red. | E20: RNF1: Cada transacción debe procesarse en menos de 200 milisegundos bajo carga normal. RNF2: El motor transaccional debe garantizar propiedades ACID en todas las operaciones. RNF3: El sistema debe soportar picos de carga (ej. fin de mes) sin degradar el SLA de procesamiento.
A21: HU18 | C21: Como sistema contable, quiero registrar débitos y créditos con partida doble e identificador único universal (UUID) para mantener la integridad financiera. | D21: RF1: Registrar cada operación con su respectivo débito y crédito en partida doble. RF2: Asignar un identificador único universal (UUID) a cada asiento contable. RF3: Ejecutar un cierre contable automatizado diario verificando que el balance esté cuadrado. | E21: RNF1: Ningún asiento debe quedar aplicado parcialmente ante una falla (atomicidad). RNF2: El cierre contable diario debe ejecutarse en una ventana definida sin afectar la operación diurna. RNF3: Los registros contables deben ser auditables y trazables por el periodo mínimo exigido por la regulación.
A22: HU19 | C22: Como analista de operaciones, quiero ejecutar conciliaciones automáticas entre el banco, las redes externas y la billetera para detectar inconsistencias de liquidación. | D22: RF1: Procesar automáticamente los archivos de compensación (clearing) de las redes externas. RF2: Comparar las operaciones del banco contra redes externas y billetera para detectar diferencias. RF3: Generar reporte de inconsistencias y habilitar el flujo de reclamos. | E22: RNF1: La conciliación diaria debe completarse antes del inicio de operaciones del siguiente día hábil. RNF2: El sistema debe procesar archivos de gran volumen sin pérdida de registros. RNF3: Las diferencias detectadas deben quedar documentadas con evidencia para su seguimiento.
A23: HU20 | B23: Épica 6 – Fraude y Cumplimiento | C23: Como analista de fraude, quiero recibir alertas automáticas por intentos de suplantación facial, geolocalización atípica o transacciones inusuales para mitigar pérdidas. | D23: RF1: Detectar intentos de suplantación facial (deepfake/spoofing) durante la autenticación. RF2: Identificar geolocalización atípica o transacciones inusuales según el comportamiento del cliente. RF3: Bloquear preventivamente una operación ante una alerta de alto riesgo y mostrarla en un tablero. | E23: RNF1: Las alertas de fraude deben generarse en tiempo real (menos de 1 segundo desde el evento). RNF2: El motor antifraude debe permitir actualizar sus reglas/modelos sin detener el servicio. RNF3: La tasa de falsos positivos debe mantenerse dentro del umbral definido por el negocio.
A24: HU21 | C24: Como oficial de cumplimiento, quiero cotejar clientes y transacciones contra listas restrictivas (OFAC, World-Check, PEP) para cumplir leyes antilavado. | D24: RF1: Cotejar a cada cliente contra listas restrictivas (OFAC, World-Check, PEP) en el onboarding. RF2: Validar las transacciones en tiempo real contra las mismas listas restrictivas. RF3: Generar un reporte de operación sospechosa (ROS) ante coincidencias relevantes. | E24: RNF1: El cotejo contra listas restrictivas debe ejecutarse en menos de 2 segundos por transacción. RNF2: Las listas restrictivas deben actualizarse de forma periódica y automática. RNF3: El resultado de cada validación debe registrarse para auditorías regulatorias (SBS/UIF).
A25: HU22 | C25: Como cliente, quiero recibir alertas push y correos instantáneos por cada transacción o login biométrico para detectar cualquier actividad no autorizada. | D25: RF1: Enviar una alerta push inmediata por cada transacción o inicio de sesión biométrico. RF2: Enviar un correo con el mismo detalle de la alerta como respaldo. RF3: Permitir al cliente reportar una actividad como no reconocida desde la notificación. | E25: RNF1: Las notificaciones deben entregarse en menos de 5 segundos desde el evento. RNF2: El sistema debe soportar múltiples canales sin perder mensajes ante la caída de un proveedor. RNF3: El reporte de actividad no reconocida debe escalar automáticamente al módulo antifraude.
A26: HU23 | C26: Como auditor, quiero consultar registros inalterables y con marca de tiempo de todos los cambios administrativos y verificaciones faciales para respaldar auditorías. | D26: RF1: Registrar todo cambio administrativo y verificación facial en un log append-only. RF2: Aplicar un hash criptográfico a cada registro almacenado. RF3: Permitir al auditor consultar registros filtrando por fecha, usuario o tipo de evento. | E26: RNF1: El log debe garantizar no repudio e impedir la modificación o eliminación de registros. RNF2: La bitácora debe conservar los registros por el periodo mínimo exigido por la regulación vigente. RNF3: Las consultas de auditoría no deben impactar el rendimiento de los sistemas transaccionales en producción.
A27: HU24 | B27: Épica 7 – Productos Avanzados | C27: Como cliente, quiero aperturar bolsillos de ahorro y cuentas en USD/EUR para organizar mis metas con reglas de redondeo automático. | D27: RF1: Aperturar bolsillos de ahorro y cuentas en USD/EUR desde la app. RF2: Configurar reglas de redondeo automático hacia una meta de ahorro. RF3: Traspasar fondos entre bolsillos y cuentas del mismo cliente. | E27: RNF1: El cálculo y acreditación de rendimientos debe ejecutarse de forma automática y periódica. RNF2: Los traspasos entre bolsillos deben reflejarse en el saldo en menos de 5 segundos. RNF3: El sistema debe soportar múltiples monedas sin errores de redondeo en las conversiones.
A28: HU25 | C28: Como cliente, quiero comprar y vender divisas con tipo de cambio competitivo en tiempo real para optimizar mi dinero. | D28: RF1: Mostrar la cotización de cambio de divisas en tiempo real. RF2: Congelar la cotización mostrada durante 30 segundos. RF3: Ejecutar la compra/venta de divisas al confirmar dentro del tiempo vigente. | E28: RNF1: La cotización debe actualizarse en tiempo real desde el proveedor de tipo de cambio. RNF2: El sistema debe rechazar automáticamente la operación si la cotización congelada expiró. RNF3: El spread aplicado debe ser configurable por el área de tesorería sin cambios de código.
A29: HU26 | C29: Como cliente, quiero programar la distribución automática de mi sueldo en porcentajes apenas ingrese mi pago para presupuestar sin esfuerzo. | D29: RF1: Permitir programar reglas de distribución automática por porcentaje sobre los ingresos. RF2: Ejecutar la dispersión automática hacia facturas, ahorros e inversión al recibir un abono masivo. RF3: Validar que la suma de los porcentajes configurados no exceda el 100%. | E29: RNF1: La dispersión automática debe ejecutarse en menos de 10 segundos tras detectar el abono. RNF2: El sistema debe notificar al cliente el detalle de cada distribución ejecutada en tiempo real. RNF3: Las reglas de distribución deben poder modificarse sin afectar distribuciones ya ejecutadas.

Sheet Backlog
A1: Product Backlog Priorizado
A3: Orden | B3: ID | C3: Épica | D3: Historia de Usuario | E3: Prioridad | F3: Story Points | G3: En MVP | H3: Sprint | I3: Dependencia | J3: Módulo | K3: Rol
A4: 1 | B4: HU01 | C4: Épica 1 – Identidad, Biometría y KYC | D4: Como cliente nuevo, quiero registrarme escaneando mi documento de identidad y validando mi rostro con Liveness Detection para aperturar mi cuenta digital de forma segura sin ir a una agencia. | E4: Must | F4: 8 | G4: Sí | H4: Sprint 1 | I4: Ninguna | J4: Registro y KYC Biométrico | K4: Cliente
A5: 2 | B5: HU02 | C5: Épica 1 – Identidad, Biometría y KYC | D5: Como cliente nuevo, quiero confirmar mi registro mediante un código de verificación enviado a mi correo o celular para activar mi cuenta digital antes de iniciar sesión por primera vez. | E5: Must | F5: 3 | G5: Sí | H5: Sprint 1 | I5: HU01 | J5: Verificación y Activación de Cuenta | K5: Cliente
A6: 3 | B6: HU03 | C6: Épica 1 – Identidad, Biometría y KYC | D6: Como cliente, quiero ingresar a la banca móvil mediante reconocimiento facial rápido o biométricos secundarios (Huella/PIN) para acceder sin recordar contraseñas complejas. | E6: Must | F6: 5 | G6: Sí | H6: Sprint 1 | I6: HU01-HU02 | J6: Autenticación BioFacial y Multi-factor | K6: Cliente
A7: 6 | B7: HU04 | C7: Épica 1 – Identidad, Biometría y KYC | D7: Como cliente, quiero recuperar mi acceso o desbloquear mi usuario mediante re-validación de biometría facial para restablecer mis credenciales de forma autónoma. | E7: Should | F7: 5 | G7: Sí | H7: Sprint 1 | I7: HU02-HU03 | J7: Recuperación de Cuenta con Biometría | K7: Cliente
A8: 4 | B8: HU05 | C8: Épica 2 – Cuentas y Transacciones | D8: Como cliente, quiero consultar saldos disponibles, fondos retenidos y movimientos en tiempo real para mantener control de mi patrimonio. | E8: Must | F8: 5 | G8: Sí | H8: Sprint 1 | I8: HU01-HU02 | J8: Consolidado de Cuentas y Saldos | K8: Cliente
A9: 5 | B9: HU06 | C9: Épica 2 – Cuentas y Transacciones | D9: Como cliente, quiero transferir dinero entre mis cuentas y a terceros (mismo banco o interbancarias inmediatas) para mover mis fondos sin comisión oculta. | E9: Must | F9: 8 | G9: Sí | H9: Sprint 1 | I9: HU05 | J9: Transferencias Propias e Interbancarias | K9: Cliente
A10: 11 | B10: HU07 | C10: Épica 2 – Cuentas y Transacciones | D10: Como cliente, quiero guardar y agrupar beneficiarios frecuentes con alias y fotos para reducir errores en transferencias recurrentes. | E10: Should | F10: 3 | G10: Sí | H10: Sprint 2 | I10: HU06 | J10: Gestión de Beneficiarios Frecuentes | K10: Cliente
A11: 7 | B11: HU08 | C11: Épica 2 – Cuentas y Transacciones | D11: Como cliente, quiero confirmar transferencias de alto monto mediante escaneo facial instantáneo para garantizar que nadie transfiera sin mi presencia física, y que el sistema restrinja transacciones según mi perfil de riesgo. | E11: Must | F11: 8 | G11: Sí | H11: Sprint 2 | I11: HU02, HU06 | J11: Autorización Biométrico-Facial de Pagos Altamente Sensibles | K11: Cliente
A12: 12 | B12: HU09 | C12: Épica 3 – Créditos Digitales | D12: Como cliente, quiero simular monto, plazo, tasa TCEA y cuota estimada para evaluar opciones de financiamiento antes de solicitar un crédito. | E12: Should | F12: 5 | G12: Sí | H12: Sprint 2 | I12: HU05 | J12: Simulador Inteligente de Créditos | K12: Cliente
A13: 8 | B13: HU10 | C13: Épica 3 – Créditos Digitales | D13: Como cliente, quiero solicitar un préstamo digital y autorizar la consulta en centrales de riesgo para recibir una respuesta de aprobación inmediata. | E13: Must | F13: 8 | G13: Sí | H13: Sprint 2 | I13: HU01, HU09 | J13: Solicitud y Evaluación Crediticia Automática | K13: Cliente
A14: 9 | B14: HU11 | C14: Épica 3 – Créditos Digitales | D14: Como cliente, quiero firmar digitalmente mi contrato de préstamo validando mi rostro como consentimiento explícito para legalizar la operación sin papeleo. | E14: Must | F14: 8 | G14: Sí | H14: Sprint 2 | I14: HU10 | J14: Firma Digital de Contrato con Biometría Facial | K14: Cliente
A15: 10 | B15: HU12 | C15: Épica 3 – Créditos Digitales | D15: Como cliente, quiero recibir el desembolso directamente en mi cuenta elegida y visualizar mi cronograma de pagos definitivo para abonar mis cuotas a tiempo. | E15: Must | F15: 5 | G15: Sí | H15: Sprint 2 | I15: HU05, HU11 | J15: Desembolso Inmediato y Programación de Cuotas | K15: Cliente
... A18: 15 | B18: HU15 | C18: Épica 4 – Billetera y Pagos QR | D18: Como cliente, quiero escanear un código QR para verificar la información del comercio y pagar en un solo toque. | E18: Must | F18: 5 | G18: Sí | H18: Sprint 3 | I18: HU14, HU17-HU18 | J18: Lectura y Confirmación de Pago QR | K18: Cliente
A19: 19 | B19: HU16 | C19: Épica 4 – Billetera y Pagos QR | D19: Como cliente, quiero pagar servicios básicos (luz, agua, internet) y recargar celulares desde la app para gestionar mis pagos en un solo lugar. | E19: Should | F19: 5 | G19: Sí | H19: Sprint 3 | I19: HU05, HU17-HU18 | J19: Pago de Servicios y Recargas Express
A20: 16 | B20: HU17 | C20: Épica 5 – Motor Transaccional | D20: Como sistema core bancario, quiero procesar transacciones con control de saldos, bloqueo de fondos y prevención de doble gasto para asegurar la consistencia operativa. | E20: Must | F20: 13 | G20: Sí | H20: Sprint 3 | I20: HU02, HU05 | J20: Motor Transaccional en Tiempo Real | K20: Sistema
A21: 17 | B21: HU18 | C21: Épica 5 – Motor Transaccional | D21: Como sistema contable, quiero registrar débitos y créditos con partida doble e identificador único universal (UUID) para mantener la integridad financiera. | E21: Must | F21: 13 | G21: Sí | H21: Sprint 3 | I21: HU17 | J21: Contabilidad en Libro Mayor (Ledger) de Partida Doble | K21: Analista de operaciones
A22: 18 | B22: HU19 | C22: Épica 5 – Motor Transaccional | D22: Como analista de operaciones, quiero ejecutar conciliaciones automáticas entre el banco, las redes externas y la billetera para detectar inconsistencias de liquidación. | E22: Must | F22: 8 | G22: Sí | H22: Sprint 3 | I22: HU18 | J22: Conciliación Bancaria y Redes de Pago | K22: Cliente
A23: 20 | B23: HU20 | C23: Épica 6 – Fraude y Cumplimiento | D23: Como analista de fraude, quiero recibir alertas automáticas por intentos de suplantación facial, geolocalización atípica o transacciones inusuales para mitigar pérdidas. | E23: Must | F23: 8 | G23: Sí | H23: Sprint 4 | I23: HU17 | J23: Motor Antifraude por Reglas y Anomalías Biométricas | K23: Analista de fraude
A24: 21 | B24: HU21 | C24: Épica 6 – Fraude y Cumplimiento | D24: Como oficial de cumplimiento, quiero cotejar clientes y transacciones contra listas restrictivas (OFAC, World-Check, PEP) para cumplir leyes antilavado. | E24: Must | F24: 8 | G24: Sí | H24: Sprint 4 | I24: HU03, HU20 | J24: Cumplimiento PLDFT / AML y Listas Restrictivas | K24: Oficial de cumplimiento
A25: 22 | B25: HU22 | C25: Épica 6 – Fraude y Cumplimiento | D25: Como cliente, quiero recibir alertas push y correos instantáneos por cada transacción o login biométrico para detectar cualquier actividad no autorizada. | E25: Should | F25: 3 | G25: Sí | H25: Sprint 4 | I25: HU17 | J25: Notificaciones de Seguridad Multicanal | K25: Cliente
A26: 21 | B26: HU22 | C26: FRAUDE, AUDITORÍA Y CUMPLIMIENTO | D26: Como cliente, quiero recibir una constancia y alerta inmediata por cada movimiento para detectar actividad desconocida. | E26: Should | F26: 3 | G26: Sí | H26: Sprint 4 | I26: HU17 | J26: Notificaciones | K26: Cliente
A27: 25 | B27: HU23 | C27: Épica 6 – Fraude y Cumplimiento | D27: Como auditor, quiero consultar registros inalterables y con marca de tiempo de todos los cambios administrativos y verificaciones faciales para respaldar auditorías. | E27: Could | F27: 5 | G27: No | H27: Sprint 4 | I27: HU03, HU18, HU21 | J27: Bitácora de Auditoría Inalterable (Audit Log) | K27: Auditor
A28: 23 | B28: HU24 | C28: Épica 7 – Productos Avanzados | D28: Como cliente, quiero aperturar bolsillos de ahorro y cuentas en USD/EUR para organizar mis metas con reglas de redondeo automático. | E28: Should | F28: 5 | G28: Sí | H28: Sprint 4 | I28: HU05, HU17-HU18 | J28: Cuentas Multidivisa y Meta de Ahorro Automático | K28: Cliente
A29: 24 | B29: HU25 | C29: Épica 7 – Productos Avanzados | D29: Como cliente, quiero comprar y vender divisas con tipo de cambio competitivo en tiempo real para optimizar mi dinero. | E29: Should | F29: 8 | G29: Sí | H29: Sprint 4 | I29: HU05, HU17-HU18 | J29: Módulo de Cambio de Divisas Preferencial | K29: Cliente
A30: 26 | B30: HU26 | C30: Épica 7 – Productos Avanzados | D30: Como cliente, quiero programar la distribución automática de mi sueldo en porcentajes apenas ingrese mi pago para presupuestar sin esfuerzo. | E30: Could | F30: 8 | G30: No | H30: Sprint 4 | I30: HU05, HU17-HU18 | J30: Distribución Automática de Ingresos y Nómina | K30: Cliente

Sheet Plan de Sprints
A1: Plan de Sprints para el MVP
A3: Sprint | B3: Objetivo | C3: Historias | D3: Story Points | E3: Entregable | F3: MVP | G3: Inicio | H3: Duración | I3: 1 | J3: 2 | K3: 3 | L3: 4 | M3: 5 | N3: 6 | O3: 7 | P3: 8 | Q3: 9 | R3: 10 | S3: 11 | T3: 12 | U3: 12 | V3: 13 | W3: 14 | X3: 15 | Y3: 16 | Z3: 17 | AA3: 18
A4: Sprint 1 | B4: Registro con identidad biométrica (KYC), activación de cuenta y autenticación segura | C4: HU01-HU06 | D4: =SUMIF(Backlog!G4:G9,Backlog!G5,Backlog!F4:F9) -> 34 | E4: Registro de usuarios, inicio de sesión, consulta de cuentas y transferencias propias. | F4: Sí | G4: 1 | H4: 2 | I4: =IF(AND(I$3>=$G4,I$3<$G4+$H4),"PLAN","") -> PLAN | J4: =IF(AND(J$3>=$G4,J$3<$G4+$H4),"PLAN","") -> PLAN | K4: PLAN | L4: PLAN | M4: =IF(AND(M$3>=$G4,M$3<$G4+$H4),"PLAN","") | N4: =IF(AND(N$3>=$G4,N$3<$G4+$H4),"PLAN","") | O4: =IF(AND(O$3>=$G4,O$3<$G4+$H4),"PLAN","") | P4: =IF(AND(P$3>=$G4,P$3<$G4+$H4),"PLAN","") | Q4: =IF(AND(Q$3>=$G4,Q$3<$G4+$H4),"PLAN","") | R4: =IF(AND(R$3>=$G4,R$3<$G4+$H4),"PLAN","") | S4: =IF(AND(S$3>=$G4,S$3<$G4+$H4),"PLAN","") | T4: =IF(AND(T$3>=$G4,T$3<$G4+$H4),"PLAN","")
A5: Sprint 2 | B5: Autorización facial para transferencias altas y firma de contratos, junto con el ciclo digital completo de crédito (simular, solicitar, evaluar, firmar, desembolsar). | C5: HU07-HU12 | D5: =SUMIF(Backlog!G10:G15,Backlog!G5,Backlog!F10:F15) -> 37 | E5: Validación para pagos altos, lista de contactos frecuentes y módulo de préstamos. | F5: Sí | G5: 3 | H5: 2 | I5: =IF(AND(I$3>=$G5,I$3<$G5+$H5),"PLAN","") | J5: =IF(AND(J$3>=$G5,J$3<$G5+$H5),"PLAN","") | L5: PLAN | M5: PLAN | N5: PLAN | O5: PLAN | P5: PLAN | Q5: =IF(AND(Q$3>=$G5,Q$3<$G5+$H5),"PLAN","") | R5: =IF(AND(R$3>=$G5,R$3<$G5+$H5),"PLAN","") | S5: =IF(AND(S$3>=$G5,S$3<$G5+$H5),"PLAN","") | T5: =IF(AND(T$3>=$G5,T$3<$G5+$H5),"PLAN","")
A6: Sprint 3 | B6: Consolidar los medios de pago (billetera, QR, servicios/recargas) sobre un motor transaccional en tiempo real con contabilidad y conciliación confiables. | C6: HU13-HU19 | D6: =SUMIF(Backlog!G16:G22,Backlog!G22,Backlog!F16:F22) -> 57 | E6: Pagos y cobros con código QR, pago de servicios básicos y registro contable. | F6: Sí | G6: 5 | H6: 2 | I6: =IF(AND(I$3>=$G6,I$3<$G6+$H6),"PLAN","") | J6: =IF(AND(J$3>=$G6,J$3<$G6+$H6),"PLAN","") | K6: =IF(AND(K$3>=$G6,K$3<$G6+$H6),"PLAN","") | L6: =IF(AND(L$3>=$G6,L$3<$G6+$H6),"PLAN","") | O6: =IF(AND(O$3>=$G6,O$3<$G6+$H6),"PLAN","") | P6: PLAN | Q6: PLAN | R6: PLAN | S6: PLAN | T6: PLAN
A7: Sprint 4 | B7: Blindar el banco digital con antifraude y cumplimiento PLDFT/AML, y ampliar la propuesta de valor con cuentas multidivisa, cambio de divisas y distribución automática de ingresos. | C7: HU20-HU26 | D7: 32 | E7: Alertas por movimientos, verificación de seguridad y compra/venta de moneda extranjera. | F7: Sí | G7: 7 | H7: 2 | I7: =IF(AND(I$3>=$G7,I$3<$G7+$H7),"PLAN","") | J7: =IF(AND(J$3>=$G7,J$3<$G7+$H7),"PLAN","") | K7: =IF(AND(K$3>=$G7,K$3<$G7+$H7),"PLAN","") | L7: =IF(AND(L$3>=$G7,L$3<$G7+$H7),"PLAN","") | M7: =IF(AND(M$3>=$G7,M$3<$G7+$H7),"PLAN","") | N7: =IF(AND(N$3>=$G7,N$3<$G7+$H7),"PLAN","") | Q7: =IF(AND(Q$3>=$G7,Q$3<$G7+$H7),"PLAN","") | R7: =IF(AND(R$3>=$G7,R$3<$G7+$H7),"PLAN","") | S7: =IF(AND(S$3>=$G7,S$3<$G7+$H7),"PLAN","") | T7: =IF(AND(T$3>=$G7,T$3<$G7+$H7),"PLAN","") | U7: PLAN | V7: PLAN | W7: PLAN | X7: PLAN | Y7: PLAN
A9: RESUMEN MVP | B9: Historias | C9: Story Points | D9: Duración
A10: Resultado | B10: =COUNTIF('[1]Backlog Priorizado'!$G$4:$G$26,"Sí") -> 22 | C10: =SUM(D4:D7) -> 160 | D10: 12 semanas

Sheet Gantt
A1: Diagrama de Gantt - 18 Semanas
A3: Semana actual | B3: 5 | D3: Semana de exposición | E3: 18 | G3: Periodo de ejecución: Semanas 1-17
A5: ID | B5: Fase / Sprint | C5: Actividad | D5: Responsable | E5: Inicio | F5: Duración | G5: Estado | H5: Entregable | I5: 1 | J5: 2 | K5: 3 | L5: 4 | M5: 5 | N5: 6 | O5: 7 | P5: 8 | Q5: 9 | R5: 10 | S5: 11 | T5: 12 | U5: 13 | V5: 14 | W5: 15 | X5: 16 | Y5: 17 | Z5: 18
A6: T01 | B6: Inicio | C6: Formación del equipo, Scrum Master, Drive y repositorio | D6: Jair + todo el equipo | E6: 1 | F6: 1 | G6: =IF(E6+F6-1<$B$3,"Completado",IF(AND(E6<=$B$3,E6+F6-1>=$B$3),"En progreso","Pendiente")) -> Completado | H6: Equipo organizado y repositorio creado | I6: =IF(AND(I$5>=$E6,I$5<$E6+$F6),"PLAN","") -> PLAN | J6: =IF(AND(J$5>=$E6,J$5<$E6+$F6),"PLAN","") | K6: =IF(AND(K$5>=$E6,K$5<$E6+$F6),"PLAN","") | L6: =IF(AND(L$5>=$E6,L$5<$E6+$F6),"PLAN","") | M6: =IF(AND(M$5>=$E6,M$5<$E6+$F6),"PLAN","") | N6: =IF(AND(N$5>=$E6,N$5<$E6+$F6),"PLAN","") | O6: =IF(AND(O$5>=$E6,O$5<$E6+$F6),"PLAN","") | P6: =IF(AND(P$5>=$E6,P$5<$E6+$F6),"PLAN","") | ... Z6: =IF(AND(Z$5>=$E6,Z$5<$E6+$F6),"PLAN","")
A7: T02 | B7: Análisis | C7: Investigación, épicas, historias, criterios y backlog | D7: Jair + todo el equipo | E7: 2 | F7: 1 | G7: =IF(E7+F7-1<$B$3,"Completado",IF(AND(E7<=$B$3,E7+F7-1>=$B$3),"En progreso","Pendiente")) -> Completado | H7: Excel de avance y alcance priorizado | I7: =IF(AND(I$5>=$E7,I$5<$E7+$F7),"PLAN","") | J7: =IF(AND(J$5>=$E7,J$5<$E7+$F7),"PLAN","") -> PLAN | K7: =IF(AND(K$5>=$E7,K$5<$E7+$F7),"PLAN","") | L7: =IF(AND(L$5>=$E7,L$5<$E7+$F7),"PLAN","") | M7: =IF(AND(M$5>=$E7,M$5<$E7+$F7),"PLAN","") | N7: =IF(AND(N$5>=$E7,N$5<$E7+$F7),"PLAN","") | O7: =IF(AND(O$5>=$E7,O$5<$E7+$F7),"PLAN","") | P7: =IF(AND(P$5>=$E7,P$5<$E7+$F7),"PLAN","") | ... Z7: =IF(AND(Z$5>=$E7,Z$5<$E7+$F7),"PLAN","")
A8: T03 | B8: Diseño | C8: Arquitectura, prototipo UX y definición de integraciones | D8: Jeremy + Jheampierre + Andersson | E8: 2 | F8: 1 | G8: =IF(E8+F8-1<$B$3,"Completado",IF(AND(E8<=$B$3,E8+F8-1>=$B$3),"En progreso","Pendiente")) -> Completado | H8: Arquitectura y prototipo navegable | I8: =IF(AND(I$5>=$E8,I$5<$E8+$F8),"PLAN","") | J8: =IF(AND(J$5>=$E8,J$5<$E8+$F8),"PLAN","") -> PLAN | K8: =IF(AND(K$5>=$E8,K$5<$E8+$F8),"PLAN","") | L8: =IF(AND(L$5>=$E8,L$5<$E8+$F8),"PLAN","") | M8: =IF(AND(M$5>=$E8,M$5<$E8+$F8),"PLAN","") | N8: =IF(AND(N$5>=$E8,N$5<$E8+$F8),"PLAN","") | O8: =IF(AND(O$5>=$E8,O$5<$E8+$F8),"PLAN","") | P8: =IF(AND(P$5>=$E8,P$5<$E8+$F8),"PLAN","") | ... Z8: =IF(AND(Z$5>=$E8,Z$5<$E8+$F8),"PLAN","")
A9: T04 | B9: Preparación | C9: Modelo de datos, contratos API, entornos y CI | D9: Andersson + Jeremy + integrante pendiente | E9: 2 | F9: 1 | G9: =IF(E9+F9-1<$B$3,"Completado",IF(AND(E9<=$B$3,E9+F9-1>=$B$3),"En progreso","Pendiente")) -> Completado | H9: Base técnica preparada | I9: =IF(AND(I$5>=$E9,I$5<$E9+$F9),"PLAN","") | J9: =IF(AND(J$5>=$E9,J$5<$E9+$F9),"PLAN","") -> PLAN | K9: =IF(AND(K$5>=$E9,K$5<$E9+$F9),"PLAN","") | L9: =IF(AND(L$5>=$E9,L$5<$E9+$F9),"PLAN","") | M9: =IF(AND(M$5>=$E9,M$5<$E9+$F9),"PLAN","") | N9: =IF(AND(N$5>=$E9,N$5<$E9+$F9),"PLAN","") | O9: =IF(AND(O$5>=$E9,O$5<$E9+$F9),"PLAN","") | P9: =IF(AND(P$5>=$E9,P$5<$E9+$F9),"PLAN","") | ... Z9: =IF(AND(Z$5>=$E9,Z$5<$E9+$F9),"PLAN","")
A10: T05 | B10: Sprint 1 | C10: Identidad, autenticación y gobierno de accesos | D10: Jeremy + Jheampierre + Gian Piero | E10: 3 | F10: 3 | G10: Completado | H10: Acceso seguro y roles | I10: =IF(AND(I$5>=$E10,I$5<$E10+$F10),"PLAN","") | J10: =IF(AND(J$5>=$E10,J$5<$E10+$F10),"PLAN","") | K10: =IF(AND(K$5>=$E10,K$5<$E10+$F10),"PLAN","") -> PLAN | L10: =IF(AND(L$5>=$E10,L$5<$E10+$F10),"PLAN","") -> PLAN | M10: =IF(AND(M$5>=$E10,M$5<$E10+$F10),"PLAN","") -> PLAN | N10: =IF(AND(N$5>=$E10,N$5<$E10+$F10),"PLAN","") | O10: =IF(AND(O$5>=$E10,O$5<$E10+$F10),"PLAN","") | P10: =IF(AND(P$5>=$E10,P$5<$E10+$F10),"PLAN","") | ... Z10: =IF(AND(Z$5>=$E10,Z$5<$E10+$F10),"PLAN","")
A11: T07 | B11: Sprint 2 | C11: Transferencias propias, terceros, beneficiarios y antifraude | D11: Jeremy + Gian Piero | E11: 4 | F11: 4 | G11: =IF(E11+F11-1<$B$3,"Completado",IF(AND(E11<=$B$3,E11+F11-1>=$B$3),"En progreso","Pendiente")) -> En progreso | H11: Transferencias trazables | I11: =IF(AND(I$5>=$E11,I$5<$E11+$F11),"PLAN","") | J11: =IF(AND(J$5>=$E11,J$5<$E11+$F11),"PLAN","") | K11: =IF(AND(K$5>=$E11,K$5<$E11+$F11),"PLAN","") | L11: =IF(AND(L$5>=$E11,L$5<$E11+$F11),"PLAN","") -> PLAN | M11: =IF(AND(M$5>=$E11,M$5<$E11+$F11),"PLAN","") -> PLAN | N11: =IF(AND(N$5>=$E11,N$5<$E11+$F11),"PLAN","") -> PLAN | O11: =IF(AND(O$5>=$E11,O$5<$E11+$F11),"PLAN","") -> PLAN | P11: =IF(AND(P$5>=$E11,P$5<$E11+$F11),"PLAN","") | ... Z11: =IF(AND(Z$5>=$E11,Z$5<$E11+$F11),"PLAN","")
A12: T08 | B12: Sprint 2 | C12: Préstamos: simulación, solicitud, evaluación y desembolso | D12: Andersson + Jheampierre + Jeremy | E12: 7 | F12: 4 | G12: =IF(E12+F12-1<$B$3,"Completado",IF(AND(E12<=$B$3,E12+F12-1>=$B$3),"En progreso","Pendiente")) -> Pendiente | H12: Ciclo digital de préstamos | I12: =IF(AND(I$5>=$E12,I$5<$E12+$F12),"PLAN","") | J12: =IF(AND(J$5>=$E12,J$5<$E12+$F12),"PLAN","") | K12: =IF(AND(K$5>=$E12,K$5<$E12+$F12),"PLAN","") | L12: =IF(AND(L$5>=$E12,L$5<$E12+$F12),"PLAN","") | M12: =IF(AND(M$5>=$E12,M$5<$E12+$F12),"PLAN","") | N12: =IF(AND(N$5>=$E12,N$5<$E12+$F12),"PLAN","") | O12: =IF(AND(O$5>=$E12,O$5<$E12+$F12),"PLAN","") -> PLAN | P12: =IF(AND(P$5>=$E12,P$5<$E12+$F12),"PLAN","") -> PLAN | ... Z12: =IF(AND(Z$5>=$E12,Z$5<$E12+$F12),"PLAN","")
A13: T06 | B13: Sprint 3 | C13: Cuentas, motor transaccional y libro mayor | D13: Andersson + Jeremy | E13: 10 | F13: 5 | G13: =IF(E13+F13-1<$B$3,"Completado",IF(AND(E13<=$B$3,E13+F13-1>=$B$3),"En progreso","Pendiente")) -> Pendiente | H13: Núcleo de saldos y contabilidad | I13: =IF(AND(I$5>=$E13,I$5<$E13+$F13),"PLAN","") | J13: =IF(AND(J$5>=$E13,J$5<$E13+$F13),"PLAN","") | K13: =IF(AND(K$5>=$E13,K$5<$E13+$F13),"PLAN","") | L13: =IF(AND(L$5>=$E13,L$5<$E13+$F13),"PLAN","") | M13: =IF(AND(M$5>=$E13,M$5<$E13+$F13),"PLAN","") | N13: =IF(AND(N$5>=$E13,N$5<$E13+$F13),"PLAN","") | O13: =IF(AND(O$5>=$E13,O$5<$E13+$F13),"PLAN","") | P13: =IF(AND(P$5>=$E13,P$5<$E13+$F13),"PLAN","") | ... Z13: =IF(AND(Z$5>=$E13,Z$5<$E13+$F13),"PLAN","")
A14: T09 | B14: Sprint 3 | C14: Billetera digital y pagos QR | D14: Jheampierre + Jeremy | E14: 13 | F14: 3 | G14: =IF(E14+F14-1<$B$3,"Completado",IF(AND(E14<=$B$3,E14+F14-1>=$B$3),"En progreso","Pendiente")) -> Pendiente | H14: Pago QR completo | I14: =IF(AND(I$5>=$E14,I$5<$E14+$F14),"PLAN","") | J14: =IF(AND(J$5>=$E14,J$5<$E14+$F14),"PLAN","") | K14: =IF(AND(K$5>=$E14,K$5<$E14+$F14),"PLAN","") | L14: =IF(AND(L$5>=$E14,L$5<$E14+$F14),"PLAN","") | M14: =IF(AND(M$5>=$E14,M$5<$E14+$F14),"PLAN","") | N14: =IF(AND(N$5>=$E14,N$5<$E14+$F14),"PLAN","") | O14: =IF(AND(O$5>=$E14,O$5<$E14+$F14),"PLAN","") | P14: =IF(AND(P$5>=$E14,P$5<$E14+$F14),"PLAN","") | ... Z14: =IF(AND(Z$5>=$E14,Z$5<$E14+$F14),"PLAN","")
A15: T10 | B15: Sprint 4 | C15: Conciliación, cumplimiento, alertas y estabilización | D15: Gian Piero + integrante pendiente | E15: 13 | F15: 4 | G15: =IF(E15+F15-1<$B$3,"Completado",IF(AND(E15<=$B$3,E15+F15-1>=$B$3),"En progreso","Pendiente")) -> Pendiente | H15: MVP controlado y conciliado | I15: =IF(AND(I$5>=$E15,I$5<$E15+$F15),"PLAN","") | J15: =IF(AND(J$5>=$E15,J$5<$E15+$F15),"PLAN","") | K15: =IF(AND(K$5>=$E15,K$5<$E15+$F15),"PLAN","") | L15: =IF(AND(L$5>=$E15,L$5<$E15+$F15),"PLAN","") | M15: =IF(AND(M$5>=$E15,M$5<$E15+$F15),"PLAN","") | N15: =IF(AND(N$5>=$E15,N$5<$E15+$F15),"PLAN","") | O15: =IF(AND(O$5>=$E15,O$5<$E15+$F15),"PLAN","") | P15: =IF(AND(P$5>=$E15,P$5<$E15+$F15),"PLAN","") | ... Z15: =IF(AND(Z$5>=$E15,Z$5<$E15+$F15),"PLAN","")
A16: T11 | B16: Gestión Scrum | C16: Planning, dailies, revisión y retrospectiva | D16: Jair + todo el equipo | E16: 5 | F16: 12 | G16: =IF(E16+F16-1<$B$3,"Completado",IF(AND(E16<=$B$3,E16+F16-1>=$B$3),"En progreso","Pendiente")) -> En progreso | H16: Seguimiento de seis sprints | I16: =IF(AND(I$5>=$E16,I$5<$E16+$F16),"PLAN","") | J16: =IF(AND(J$5>=$E16,J$5<$E16+$F16),"PLAN","") | K16: =IF(AND(K$5>=$E16,K$5<$E16+$F16),"PLAN","") | L16: =IF(AND(L$5>=$E16,L$5<$E16+$F16),"PLAN","") | M16: =IF(AND(M$5>=$E16,M$5<$E16+$F16),"PLAN","") -> PLAN | N16: =IF(AND(N$5>=$E16,N$5<$E16+$F16),"PLAN","") -> PLAN | O16: =IF(AND(O$5>=$E16,O$5<$E16+$F16),"PLAN","") -> PLAN | P16: =IF(AND(P$5>=$E16,P$5<$E16+$F16),"PLAN","") -> PLAN | ... Z16: =IF(AND(Z$5>=$E16,Z$5<$E16+$F16),"PLAN","")
A17: T12 | B17: Calidad | C17: Pruebas funcionales, seguridad y regresión continua | D17: Gian Piero + desarrolladores | E17: 5 | F17: 12 | G17: =IF(E17+F17-1<$B$3,"Completado",IF(AND(E17<=$B$3,E17+F17-1>=$B$3),"En progreso","Pendiente")) -> En progreso | H17: Evidencias y defectos controlados | I17: =IF(AND(I$5>=$E17,I$5<$E17+$F17),"PLAN","") | J17: =IF(AND(J$5>=$E17,J$5<$E17+$F17),"PLAN","") | K17: =IF(AND(K$5>=$E17,K$5<$E17+$F17),"PLAN","") | L17: =IF(AND(L$5>=$E17,L$5<$E17+$F17),"PLAN","") | M17: =IF(AND(M$5>=$E17,M$5<$E17+$F17),"PLAN","") -> PLAN | N17: =IF(AND(N$5>=$E17,N$5<$E17+$F17),"PLAN","") -> PLAN | O17: =IF(AND(O$5>=$E17,O$5<$E17+$F17),"PLAN","") -> PLAN | P17: =IF(AND(P$5>=$E17,P$5<$E17+$F17),"PLAN","") -> PLAN | ... Z17: =IF(AND(Z$5>=$E17,Z$5<$E17+$F17),"PLAN","")
A18: T13 | B18: Cierre | C18: Integración completa, pruebas finales y correcciones | D18: Todo el equipo | E18: 17 | F18: 1 | G18: =IF(E18+F18-1<$B$3,"Completado",IF(AND(E18<=$B$3,E18+F18-1>=$B$3),"En progreso","Pendiente")) -> Pendiente | H18: Versión candidata a exposición | I18: =IF(AND(I$5>=$E18,I$5<$E18+$F18),"PLAN","") | J18: =IF(AND(J$5>=$E18,J$5<$E18+$F18),"PLAN","") | K18: =IF(AND(K$5>=$E18,K$5<$E18+$F18),"PLAN","") | L18: =IF(AND(L$5>=$E18,L$5<$E18+$F18),"PLAN","") | M18: =IF(AND(M$5>=$E18,M$5<$E18+$F18),"PLAN","") | N18: =IF(AND(N$5>=$E18,N$5<$E18+$F18),"PLAN","") | O18: =IF(AND(O$5>=$E18,O$5<$E18+$F18),"PLAN","") | P18: =IF(AND(P$5>=$E18,P$5<$E18+$F18),"PLAN","") | ... Z18: =IF(AND(Z$5>=$E18,Z$5<$E18+$F18),"PLAN","")
A19: T14 | B19: Cierre | C19: Documentación técnica, memoria y anexos | D19: Jair + todo el equipo | E19: 17 | F19: 1 | G19: =IF(E19+F19-1<$B$3,"Completado",IF(AND(E19<=$B$3,E19+F19-1>=$B$3),"En progreso","Pendiente")) -> Pendiente | H19: Documentación final | I19: =IF(AND(I$5>=$E19,I$5<$E19+$F19),"PLAN","") | J19: =IF(AND(J$5>=$E19,J$5<$E19+$F19),"PLAN","") | K19: =IF(AND(K$5>=$E19,K$5<$E19+$F19),"PLAN","") | L19: =IF(AND(L$5>=$E19,L$5<$E19+$F19),"PLAN","") | M19: =IF(AND(M$5>=$E19,M$5<$E19+$F19),"PLAN","") | N19: =IF(AND(N$5>=$E19,N$5<$E19+$F19),"PLAN","") | O19: =IF(AND(O$5>=$E19,O$5<$E19+$F19),"PLAN","") | P19: =IF(AND(P$5>=$E19,P$5<$E19+$F19),"PLAN","") | ... Z19: =IF(AND(Z$5>=$E19,Z$5<$E19+$F19),"PLAN","")
A20: T15 | B20: Cierre | C20: Preparación del guion y ensayo de la demostración | D20: Todo el equipo | E20: 17 | F20: 1 | G20: =IF(E20+F20-1<$B$3,"Completado",IF(AND(E20<=$B$3,E20+F20-1>=$B$3),"En progreso","Pendiente")) -> Pendiente | H20: Presentación ensayada | I20: =IF(AND(I$5>=$E20,I$5<$E20+$F20),"PLAN","") | J20: =IF(AND(J$5>=$E20,J$5<$E20+$F20),"PLAN","") | K20: =IF(AND(K$5>=$E20,K$5<$E20+$F20),"PLAN","") | L20: =IF(AND(L$5>=$E20,L$5<$E20+$F20),"PLAN","") | M20: =IF(AND(M$5>=$E20,M$5<$E20+$F20),"PLAN","") | N20: =IF(AND(N$5>=$E20,N$5<$E20+$F20),"PLAN","") | O20: =IF(AND(O$5>=$E20,O$5<$E20+$F20),"PLAN","") | P20: =IF(AND(P$5>=$E20,P$5<$E20+$F20),"PLAN","") | ... Z20: =IF(AND(Z$5>=$E20,Z$5<$E20+$F20),"PLAN","")
A21: T16 | B21: Exposición | C21: Exposición y demostración final | D21: Todo el equipo | E21: 18 | F21: 1 | G21: =IF(E21+F21-1<$B$3,"Completado",IF(AND(E21<=$B$3,E21+F21-1>=$B$3),"En progreso","Pendiente")) -> Pendiente | H21: Proyecto presentado | I21: =IF(AND(I$5>=$E21,I$5<$E21+$F21),"PLAN","") | J21: =IF(AND(J$5>=$E21,J$5<$E21+$F21),"PLAN","") | K21: =IF(AND(K$5>=$E21,K$5<$E21+$F21),"PLAN","") | L21: =IF(AND(L$5>=$E21,L$5<$E21+$F21),"PLAN","") | M21: =IF(AND(M$5>=$E21,M$5<$E21+$F21),"PLAN","") | N21: =IF(AND(N$5>=$E21,N$5<$E21+$F21),"PLAN","") | O21: =IF(AND(O$5>=$E21,O$5<$E21+$F21),"PLAN","") | P21: =IF(AND(P$5>=$E21,P$5<$E21+$F21),"PLAN","") | ... Z21: =IF(AND(Z$5>=$E21,Z$5<$E21+$F21),"PLAN","") -> PLAN

Sheet Matriz de Riesgos
A1: Matriz de Riesgos - Banco Digital con Biometría
A2: Escalas: Probabilidad (Alta/Media/Baja) x Impacto (Alto/Medio/Bajo) -> Nivel P*I. Fuente: Definición técnica de sprints HU01-HU26.
A3: ID | B3: Fase / Sprint donde se presenta | C3: Probabilidad | D3: Impacto | E3: Nivel P*I | F3: Estrategia de Mitigación | G3: Plan de Contingencia
A4: Riesgo01 | B4: Sprint 1 - KYC | C4: Media | D4: Alto | E4: Alto | F4: Entrenar el OCR con datasets diversos de documentos peruanos, validación cruzada de campos extraídos y doble captura. | G4: Reintentos limitados, captura manual asistida y derivación a revisión humana o agencia.
A5: Riesgo02 | B5: Sprint 1 - KYC | C5: Media | D5: Alto | E5: Alto | F5: Circuit breaker y reintentos con backoff exponencial hacia RENIEC, guardado parcial del progreso KYC y proveedor alternativo de verificación de identidad. | G5: Cola de registros asistidos y reprogramación de verificación diferida.
A6: Riesgo03 | B6: Sprint 1 - KYC | C6: Media | D6: Alto | E6: Alto | F6: Liveness en doble capa (on-device + servidor), umbrales parametrizables y retraining continuo frente a nuevas técnicas de spoofing/deepfake. | G6: Canal alternativo (videollamada, huella) y revisión manual por analista.
A7: Riesgo04 | B7: Sprint 1 - Activación | C7: Media | D7: Medio | E7: Medio | F7: Utilizar al menos dos proveedores de SMS/email con enrutamiento y monitoreo de entrega, límites de reenvío configurados. | G7: OTP por app con token, vía de asistencia telefónica o fallback a preguntas de seguridad.
A8: Riesgo05 | B8: Sprint 1 - Autenticación | C8: Alta | D8: Medio | E8: Medio | F8: Optimización del pipeline facial para cumplir <1,5 s, pruebas de UX con dispositivos de gama baja, fallback inmediato a huella/PIN. | G8: Umbral de degradación automática a otro factor sin perjudicar la seguridad.
A9: Riesgo06 | B9: Sprint 1 - Autenticación | C9: Media | D9: Medio | E9: Medio | F9: Captchas progresivos, bloqueo solo ante fallos consecutivos y notificaciones de seguridad a cada intento fallido. | G9: Desbloqueo autónomo por re-biometría (HU04) o asistencia de soporte.
A10: Riesgo07 | B10: Sprint 2 - Pagos sensibles | C10: Media | D10: Alto | E10: Alto | F10: Relacionar 1 a 1 el token facial con la transacción y su hash, biometric match en vivo y registro de auditoría del intento. | G10: Reversión de la operación no autorizada, congelamiento preventivo y análisis forense como evento de seguridad.
A11: Riesgo08 | B11: Sprint 2 - Firma digital | C11: Media | D11: Alto | E11: Alto | F11: Revisión legal de la validez de la firma biométrico-facial en la jurisdicción peruana, certificado digital y evidencia enlazada de consentimiento. | G11: Firma presencial o notarial como respaldo y protocolo de defensa ante impugnaciones.
A12: Riesgo09 | B12: Sprint 2 - Evaluación crediticia | C12: Media | D12: Medio | E12: Medio | F12: Validación estricta de datos obligatorios, autorización explícita del cliente para centrales de riesgo y modelos robustos ante datos incompletos. | G12: Revisión manual o escalamiento de la solicitud ante resultados no concluyentes.
A13: Riesgo10 | B13: Sprint 2 - Desembolso | C13: Baja | D13: Medio | E13: Medio | F13: Operación idempotente con identificador único, verificación de saldo en el motor y seguimiento en el ledger antes de acreditar. | G13: Reintento automático controlado, reversión del asiento y notificación al cliente.
A14: Riesgo11 | B14: Sprint 2 - Simulador | C14: Baja | D14: Alto | E14: Alto | F14: Cálculo de TCEA validado contra fórmulas oficiales del regulador y pruebas de exactitud sobre casos de referencia del SBS. | G14: Actualización de parámetros, corrección de simulaciones emitidas y comunicación transparente al cliente.
... A28: Riesgo25 | B28: Transversal - Todos los sprints | C28: Media | D28: Alto | E28: Alto | F28: Cumplimiento de la normativa de protección de datos personales, cifrado de datos biométricos en reposo/tránsito, consentimientos explícitos y minimización de datos. | G28: Notificación de incidentes al regulador, plan de respuesta a brechas y suspensión temporal de funcionalidades afectadas.

Sheet Flujo Financiero
A1: Cómo se Procesa el Dinero
A3: Operación | B3: Etapa | C3: Responsable | D3: Qué ocurre | E3: Estado | F3: Control principal | G3: Efecto en el dinero | H3: Quién lo visualiza
A4: Transferencia | B4: 1. Solicitud | C4: Cliente | D4: Ingresa cuenta destino e importe y confirma. | E4: Iniciada | F4: Validar cuenta, beneficiario y formato. | G4: Sin movimiento | H4: Cliente
A5: Transferencia | B5: 2. Autorización | C5: Cliente / Fraude | D5: MFA y evaluación de límites y riesgo. | E5: Validada o rechazada | F5: Biometría/OTP, dispositivo, velocidad y listas de riesgo. | G5: Sin movimiento | H5: Cliente y Fraude
A6: Transferencia | B6: 3. Reserva | C6: Motor transaccional | D6: Reserva el importe y evita solicitudes duplicadas. | E6: Autorizada | F6: Saldo suficiente e idempotencia. | G6: Disponible baja; retenido sube | H6: Cliente y Operaciones
A7: Transferencia | B7: 4. Contabilización | C7: Libro mayor | D7: Registra débito y crédito de manera atómica. | E7: Contabilizada | F7: Partida doble y ID único. | G7: Débito origen / crédito destino o tránsito | H7: Operaciones y Auditoría
A8: Transferencia | B8: 5. Liquidación | C8: Red / Banco receptor | D8: Confirma la entrega de fondos al destino. | E8: Liquidada | F8: Canal cifrado y respuesta final. | G8: Fondos entregados | H8: Cliente y Operaciones
A9: Transferencia | B9: 6. Conciliación | C9: Analista de operaciones | D9: Compara libro mayor, red y banco. | E9: Conciliada o excepción | F9: Coincidencia de ID, monto, fecha y estado. | G9: Ajuste solo si está autorizado | H9: Operaciones y Cumplimiento
A10: Pago QR | B10: 1. QR y lectura | C10: Comercio / Cliente | D10: Genera y escanea QR con importe, referencia y vencimiento. | E10: Iniciada | F10: Formato interoperable y QR vigente. | G10: Sin movimiento | H10: Cliente y Comercio
A11: Pago QR | B11: 2. Pago | C11: Cliente / Motor | D11: Confirma con MFA; valida saldo, riesgo y duplicidad. | E11: Autorizada | F11: Autenticación reforzada e idempotencia. | G11: Fondos retenidos | H11: Cliente y Fraude
A12: Pago QR | B12: 3. Registro y liquidación | C12: Libro mayor / Red | D12: Contabiliza, envía y confirma el pago al comercio. | E12: Liquidada | F12: Partida doble y conciliación posterior. | G12: Débito cliente / crédito comercio | H12: Cliente, Comercio y Operaciones
A13: Préstamo | B13: 1. Solicitud | C13: Cliente | D13: Simula y presenta una solicitud autorizando la evaluación. | E13: Solicitada | F13: Consentimiento y expediente completo. | G13: Sin movimiento | H13: Cliente y Crédito
A14: Préstamo | B14: 2. Evaluación | C14: Analista de crédito | D14: Evalúa ingresos, deuda, capacidad de pago y riesgo. | E14: Aprobada, observada o rechazada | F14: Separación entre solicitud y aprobación. | G14: Sin movimiento | H14: Crédito y Cumplimiento
... A18: Excepción | B18: Reverso | C18: Operaciones autorizado | D18: Crea una operación compensatoria asociada a la original. | E18: Revertida | F18: Nunca borrar la operación original. | G18: Asientos compensatorios | H18: Operaciones, Cumplimiento y Auditoría

Sheet Matriz de acceso
A1: Matriz de Accesos y Visibilidad
A3: Rol | B3: Saldos | C3: Transferencias | D3: Préstamos | E3: Conciliación | F3: Datos personales | G3: Usuarios/permisos | H3: Auditoría | I3: Alcance / restricción
A4: Cliente | B4: Propios | C4: Propias | D4: Propios | E4: Propios | F4: Propias | G4: No | H4: No | I4: Consulta y autoriza sus operaciones
A5: Comercio | B5: Cobros propios | C5: Cobros propios | D5: No | E5: No | F5: Mínimos | G5: No | H5: No | I5: Genera QR y consulta pagos recibidos
A6: Analista de crédito | B6: Enmascarados | C6: Solo relación crediticia | D6: Expedientes asignados | E6: No | F6: Necesarios | G6: No | H6: Sí | I6: Evalúa; no desembolsa ni cambia roles
A7: Analista de operaciones | B7: Enmascarados | C7: Sí | D7: Estado de desembolso | E7: Sí | F7: Enmascarados | G7: No | H7: Sí | I7: Concilia y gestiona excepciones
A8: Analista de fraude | B8: Enmascarados | C8: Sí | D8: Alertas relacionadas | E8: Sí | F8: Necesarios | G8: No | H8: Sí | I8: Retiene o libera casos según política
A9: Oficial de cumplimiento | B9: Enmascarados | C9: Sí | D9: Sí | E9: Sí | F9: Autorizados | G9: No | H9: Sí | I9: Investiga operaciones inusuales
A10: Administrador de seguridad | B10: No | C10: No | D10: No | E10: No | F10: No | G10: Sí | H10: Sí | I10: Gestiona identidades, roles y permisos
A11: Auditor | B11: Solo lectura | C11: Solo lectura | D11: Solo lectura | E11: Solo lectura | F11: Enmascarados | G11: Solo lectura | H11: Sí | I11: Verifica evidencia; no ejecuta operaciones
A12: Servicio transaccional | B12: Técnico | C12: Procesa | D12: Desembolso autorizado | E12: Procesa | F12: Tokenizados | G12: No | H12: Sí | I12: Cuenta técnica sin acceso interactivo

Sheet Equipo y Roles
A1: Equipo Scrum y Responsabilidades
A3: N.° | B3: Integrante | C3: Rol | D3: Especialidad | E3: Responsabilidades principales | F3: Lidera | G3: Apoya | H3: Participación | I3: Observación
A4: 1 | B4: Jair Pool Conislla Bocangel | C4: Scrum Master | D4: Gestión ágil y análisis funcional | E4: Facilitar ceremonias, remover impedimentos, coordinar entregables y validar el backlog. | F4: Identidad y planificación | G4: Documentación y presentación | H4: Semanas 1-18 | I4: Primer integrante indicado por el equipo
A5: 2 | B5: Jeremy Piero Rojas Egusquiza | C5: Desarrollador Backend | D5: API y servicios bancarios | E5: Construir autenticación, servicios de cuentas, transferencias e integración con el motor transaccional. | F5: Cuentas y transferencias | G5: Préstamos y QR | H5: Semanas 2-17 | I5: Rol asignado para equilibrar el equipo
A6: 3 | B6: Jheampierre Johayro Ralli Peralta | C6: Desarrollador Frontend | D6: Interfaz y experiencia de usuario | E6: Construir pantallas de acceso, cuentas, transferencias, préstamos, billetera y pagos QR. | F6: Billetera y QR | G6: Préstamos y accesibilidad | H6: Semanas 2-17 | I6: Rol asignado para equilibrar el equipo
A7: 4 | B7: Andersson Junior Espinoza Medina | C7: Desarrollador de Datos | D7: Base de datos y lógica transaccional | E7: Diseñar modelo de datos, libro mayor, asientos, préstamos, saldos y conciliación. | F7: Procesamiento del dinero | G7: Backend e integración | H7: Semanas 2-17 | I7: Rol asignado para equilibrar el equipo
A8: 5 | B8: Gonzales Flores, Gian Piero | C8: Desarrollador QA y Seguridad | D8: Pruebas, seguridad y fraude | E8: Diseñar pruebas, validar criterios de aceptación, revisar accesos, MFA, fraude y vulnerabilidades. | F8: Seguridad y antifraude | G8: Pruebas integrales | H8: Semanas 2-17 | I8: Rol asignado para equilibrar el equipo
A9: 6 | C9: Desarrollador DevOps e Integración | D9: Entornos, automatización y observabilidad | E9: Preparar repositorio, integración continua, despliegues, registros y soporte a la integración final. | F9: Integración y despliegue | G9: QA y documentación técnica | H9: Semanas 2-17
